Workbook

Sheet FL Spill Analysis
A1: trkg_num | B1: Operator Name | C1: operator_num | D1: incident_date | E1: facility_type | F1: Spill_Desc | G1: county | H1: Spill Type | I1: Root Cause | J1: Preventative Measure | K1: Root Cause Type | L1: Detailed Root Cause Type | M1: Long | N1: Lat | O1: oil_spilled | P1: oil_recovered | Q1: cond_spilled | R1: cond_recovered | S1: PW_spilled | T1: PW_recovered | U1: drilling_spilled | V1: drilling_recovered | W1: frac_spilled | X1: frac_recovered | Y1: other_spilled | Z1: other_recovered | AA1: other_spilled_specify | AB1: facility_status | AC1: Basin | AD1: Gathering? | AE1: Metallic? | AF1: =VLOOKUP(A1,#REF!, 7, FALSE) -> #REF! | AG1: =VLOOKUP(A1,#REF!, 8, FALSE) -> #REF! | AH1: On Location? | AI1: Fac or Loc ID
A2: 400768997 | B2: PETRON DEVELOPMENT COMPANY | C2: 69760 | D2: 42005 | E2: WELL | F2: A backup restraint that keeps our drive head on our PC pumps from twisting broke. This allowed the drive head to partially rotate. That caused a crack in a 3 x 2 sedge in the flow line. Steam was seen jetting from the crack (-20 degree temps vs. 110 degree water). We immediately shut the well in and made repairs. Weather conditions this coming Monday (Jan. 5th) should allow us a better look at the ground situation. However, we are confident we have the situation resolved. The ground is frozen and any water produced from the break has evaporated. The well remains shut-in until we can determine the exact sequence that caused the failure. | G2: WASHINGTON | I2: A backup restraint that keeps our drive head on our PC pumps from twisting broke. This allowed the drive head to partially rotate. That caused a crack in a 3 x 2 sedge in the flow line. Steam was seen jetting from the crack (-20 degree temps vs. 110 degree water). We immediately shut the well in and made repairs. | J2: We replaced the restraining chain with a heavier chain. | K2: Incorrect Operation | L2: Improper Procedures | M2: -102.84418 | N2: 40.14439 | O2: 1 | Q2: 0 | S2: 40 | U2: 0 | W2: 0 | Y2: NULL | AA2: NULL | AC2: DENVER JULESBURG BASIN | AD2: =IF(OR(IFERROR(SEARCH("gathering",F2)>0,FALSE),IFERROR(SEARCH("gathering",I2)>0,FALSE)),"Gathering","Non-Gathering") -> Non-Gathering | AE2: Unknown | AF2: =VLOOKUP(A2,#REF!, 7, FALSE) -> #REF! | AG2: =VLOOKUP(A2,#REF!, 8, FALSE) -> #REF! | AI2: =VLOOKUP(A2,#REF!,40,FALSE) -> #REF!
A3: 400763041 | B3: PIONEER NATURAL RESOURCES USA INC | C3: 10084 | D3: 42006 | E3: WATER GATHERING SYSTEM/LINE | F3: One inch valve on the waterline inside the meter house froze and broke, allowing approximately 20 bbls of produced water to spill out. Some water ran into the sediment trap and stopped there. Water also ran down the lease road into a sediment trap then into a bar ditch along the main road where it stopped. The well was shut off upon discovery so that repairs can be done. | G3: LAS ANIMAS | I3: One inch valve on the waterline inside the meter house froze and broke, allowing approximately 20 bbls of produced water to spill out. Some water ran into the sediment trap and stopped there. Water also ran down the lease road into a sediment trap then into a bar ditch along the main road where it stopped. The well was shut off upon discovery so that repairs can be done. | J3: The valve has been replaced and everything is operating normally. | K3: Natural Force Damage | L3: Valve Freeze | M3: -104.90956 | N3: 37.19037 | O3: 0 | Q3: 0 | S3: 20 | U3: 0 | W3: 0 | Y3: NULL | AA3: NULL | AC3: RATON BASIN | AD3: =IF(OR(IFERROR(SEARCH("gathering",F3)>0,FALSE),IFERROR(SEARCH("gathering",I3)>0,FALSE)),"Gathering","Non-Gathering") -> Non-Gathering | AE3: Unknown | AF3: =VLOOKUP(A3,#REF!, 7, FALSE) -> #REF! | AG3: =VLOOKUP(A3,#REF!, 8, FALSE) -> #REF! | AI3: =VLOOKUP(A3,#REF!,40,FALSE) -> #REF!
A4: 400763258 | B4: DCP MIDSTREAM LP | C4: 4680 | D4: 42006 | E4: PIPELINE | F4: The release occurred as a result of a trenching machine's trenching wheel coming into contact with a below ground flow line. When the trenching wheel came in contact with the flow line, approximately 3 barrels of condensate was released into the soil subsurface trenched excavation areal. The flow line was shut in and a vac truck immediately mobilized to the location and removed approximately 2 barrels from the trenched area. At this time it appears that the majority of the release was contained in the trench and there has been no impacts to groundwater. Continued remediation activities are being scheduled to take place as soon as possible. | G4: WELD | I4: A ditcher struck an active DCP line when digging a trench for a new pipeline to be set for another company. | J4: More accurate line locates and more frequent flagging to ensure it is highly visible where the pipeline is. | K4: Excavation Force Damage | L4: Line Strike | M4: -104.71265 | N4: 40.539301 | O4: 0 | Q4: 3 | S4: 0 | U4: 0 | W4: 0 | Y4: NULL | AA4: NULL | AC4: =VLOOKUP(A4,'Basin Blanks Report'!$B$1:$F$222,3,FALSE) -> DENVER JULESBURG BASIN | AD4: =IF(OR(IFERROR(SEARCH("gathering",F4)>0,FALSE),IFERROR(SEARCH("gathering",I4)>0,FALSE)),"Gathering","Non-Gathering") -> Non-Gathering | AE4: Unknown | AF4: =VLOOKUP(A4,#REF!, 7, FALSE) -> #REF! | AG4: =VLOOKUP(A4,#REF!, 8, FALSE) -> #REF! | AI4: =VLOOKUP(A4,#REF!,40,FALSE) -> #REF!
A5: 400764687 | B5: BARRETT CORPORATION* BILL | C5: 10071 | D5: 42008 | E5: TANK BATTERY | F5: Incident still under investigation, however, preliminary investigation has indicated that the burner on the heater treater blew out and dump line froze. Oil backed up into a vapor recovery tower and a pressure relief valve on the top of the tower was actuated. Between 1 and 3 bbls of oil was released out of the top of the tower in a fine mist that covered and area approximately 125 yards long by 50 yards wide. | G5: WELD | I5: Investigation has indicated that the burner on the heater treater blew out and dump line froze. Oil backed up into a vapor recovery tower and a pressure relief valve on the top of the tower was actuated. | J5: Ensure all heaters are adequately shrouded and/or oriented to minimize the change that the burner will be blown out by high winds. | K5: Incorrect Operation | L5: Improper Procedures | M5: -104.24814 | N5: 40.46566 | O5: 2 | Q5: 0 | S5: 0 | U5: 0 | W5: 0 | Y5: NULL | AA5: NULL | AC5: =VLOOKUP(A5,'Basin Blanks Report'!$B$1:$F$222,3,FALSE) -> DENVER JULESBURG BASIN | AD5: =IF(OR(IFERROR(SEARCH("gathering",F5)>0,FALSE),IFERROR(SEARCH("gathering",I5)>0,FALSE)),"Gathering","Non-Gathering") -> Non-Gathering | AE5: Unknown | AF5: =VLOOKUP(A5,#REF!, 7, FALSE) -> #REF! | AG5: =VLOOKUP(A5,#REF!, 8, FALSE) -> #REF! | AI5: =VLOOKUP(A5,#REF!,40,FALSE) -> #REF!
A6: 400764760 | B6: PIONEER NATURAL RESOURCES USA INC | C6: 10084 | D6: 42008 | E6: WELL | F6: PC well head torqued up and broke 2" line at flow tee.The well kept pumping and pumped aproximately 2000 bbls of produced water on location, and off NE side location. Water ran NE off the pad into a dry tributary of Chimney Canyon. Water was seen flowing into the dry Chimney Canyon confluence from the P&A’d Lorencito 3-19-34-66 location, but water was not seeing flowing into Lorencito Canyon lower down Chimney Canyon at the county road crossing. | G6: LAS ANIMAS | I6: PC well head torqued up for an unknown reason and broke 2" line at flow tee. The well kept pumping and pumped aproximately 2000 bbls of produced water spilled out. | J6: The old corroded 2" pipe at the wellhead has been replaced and the well is back to operating normally and the water going to surface discharge at Outfall 076 end of pipe. | K6: Corrosion | L6: Corrosion Type Unknown | M6: -104.83202 | N6: 37.07617 | O6: 0 | Q6: 0 | S6: 2000 | U6: 0 | W6: 0 | Y6: NULL | AA6: NULL | AC6: RATON BASIN | AD6: =IF(OR(IFERROR(SEARCH("gathering",F6)>0,FALSE),IFERROR(SEARCH("gathering",I6)>0,FALSE)),"Gathering","Non-Gathering") -> Non-Gathering | AE6: Metallic | AF6: =VLOOKUP(A6,#REF!, 7, FALSE) -> #REF! | AG6: =VLOOKUP(A6,#REF!, 8, FALSE) -> #REF! | AI6: =VLOOKUP(A6,#REF!,40,FALSE) -> #REF!
A7: 400765914 | B7: XTO ENERGY INC | C7: 100264 | D7: 42009 | E7: WATER GATHERING SYSTEM/LINE | F7: Isolation valve ruptured due to freeze. Line was isolated and all contributing wells were shut in. No water was recoved. | G7: LAS ANIMAS | I7: A block valve on a dischargeable water line froze, resulting in a release of dischargeable water. | J7: It is procedure to make sure all discharge points are open and free from freeze during winter months. | K7: Natural Force Damage | L7: Valve Freeze | M7: -104.91933 | N7: 37.13948 | O7: 0 | Q7: 0 | S7: 509 | U7: 0 | W7: 0 | Y7: NULL | AA7: NULL | AC7: RATON BASIN | AD7: =IF(OR(IFERROR(SEARCH("gathering",F7)>0,FALSE),IFERROR(SEARCH("gathering",I7)>0,FALSE)),"Gathering","Non-Gathering") -> Non-Gathering | AE7: Unknown | AF7: =VLOOKUP(A7,#REF!, 7, FALSE) -> #REF! | AG7: =VLOOKUP(A7,#REF!, 8, FALSE) -> #REF! | AI7: =VLOOKUP(A7,#REF!,40,FALSE) -> #REF!
A8: 400765386 | B8: OMIMEX PETROLEUM INC | C8: 66190 | D8: 42010 | E8: FLOWLINE | F8: Flowline rupture at a gas well. Well shut-in. We used a vac truck to remove production water. Frozen production water was placed in open swab tank. Once frozen production water thaws. The water will be transported to our SWD well. | G8: YUMA | I8: #N/A | J8: #N/A | K8: Unknown | L8: Unknown | M8: -102.32982 | N8: 40.43495 | O8: NULL | Q8: NULL | S8: NULL | U8: NULL | W8: NULL | Y8: NULL | AA8: NULL | AC8: =VLOOKUP(A8,'Basin Blanks Report'!$B$1:$F$222,3,FALSE) -> DENVER JULESBURG BASIN | AD8: =IF(OR(IFERROR(SEARCH("gathering",F8)>0,FALSE),IFERROR(SEARCH("gathering",I8)>0,FALSE)),"Gathering","Non-Gathering") -> Non-Gathering | AE8: Unknown | AF8: =VLOOKUP(A8,#REF!, 7, FALSE) -> #REF! | AG8: =VLOOKUP(A8,#REF!, 8, FALSE) -> #REF! | AI8: =VLOOKUP(A8,#REF!,40,FALSE) -> #REF!
A9: 400767943 | B9: CHEVRON USA INC | C9: 16700 | D9: 42012 | E9: FLOWLINE | F9: Thursday (01-08-2015) at approximately 2:47 PM a leak occurred on an on a 3" coated steel injection line at AC McLaughlin 23. Approximately 50.4BBLs of produced water was released. The lateral valve was shut in immediately upon detection. Vacuum truck recovered an estimated 40 BBLs. The affected has been water washed and soil samples will be taken. | G9: RIO BLANCO | I9: #N/A | J9: #N/A | K9: Unknown | L9: Unknown | M9: -108.9306 | N9: 40.1265 | O9: 0 | Q9: 0 | S9: 50.4 | U9: 0 | W9: 0 | Y9: 0 | AA9: 0 | AC9: PICEANCE BASIN | AD9: =IF(OR(IFERROR(SEARCH("gathering",F9)>0,FALSE),IFERROR(SEARCH("gathering",I9)>0,FALSE)),"Gathering","Non-Gathering") -> Non-Gathering | AE9: Metallic | AF9: =VLOOKUP(A9,#REF!, 7, FALSE) -> #REF! | AG9: =VLOOKUP(A9,#REF!, 8, FALSE) -> #REF! | AI9: =VLOOKUP(A9,#REF!,40,FALSE) -> #REF!
A10: 400768543 | B10: PIONEER NATURAL RESOURCES USA INC | C10: 10084 | D10: 42014 | E10: WELL | F10: Lease Operator found 2" ball vale on water line open, water ran off location down to the county road. It did not reach waters of the State. Incident is still under investigation. | G10: LAS ANIMAS | I10: Lack of communication among Lease Operators before time off. | J10: Valve has been closed and Lease Operators spoken to about communicating better. | K10: Incorrect Operation | L10: Valve Misalignment | M10: -104.91558 | N10: 37.25979 | O10: 0 | Q10: 0 | S10: 20 | U10: 0 | W10: 0 | Y10: NULL | AA10: NULL | AC10: RATON BASIN | AD10: =IF(OR(IFERROR(SEARCH("gathering",F10)>0,FALSE),IFERROR(SEARCH("gathering",I10)>0,FALSE)),"Gathering","Non-Gathering") -> Non-Gathering | AE10: Unknown | AF10: =VLOOKUP(A10,#REF!, 7, FALSE) -> #REF! | AG10: =VLOOKUP(A10,#REF!, 8, FALSE) -> #REF! | AI10: =VLOOKUP(A10,#REF!,40,FALSE) -> #REF!
A11: 400769226 | B11: CHEVRON USA INC | C11: 16700 | D11: 42014 | E11: FLOWLINE | F11: Saturday, (01-10-2015) at approximately 8:25 AM a produced water leak occurred on the lateral injection line to FV Larson 20. Approximately 100.8 BBLs of produced water was released. The wells and lateral valve was shut in immediately upon detection. Vacuum truck recovered an estimated 75 BBLs. The affected will be water washed and soil samples will be taken. | G11: RIO BLANCO | I11: #N/A | J11: #N/A | K11: Unknown | L11: Unknown | M11: -108.7936 | N11: 40.1039 | O11: 0 | Q11: 0 | S11: 100.8 | U11: 0 | W11: 0 | Y11: 0 | AA11: 0 | AC11: PICEANCE BASIN | AD11: =IF(OR(IFERROR(SEARCH("gathering",F11)>0,FALSE),IFERROR(SEARCH("gathering",I11)>0,FALSE)),"Gathering","Non-Gathering") -> Non-Gathering | AE11: Unknown | AF11: =VLOOKUP(A11,#REF!, 7, FALSE) -> #REF! | AG11: =VLOOKUP(A11,#REF!, 8, FALSE) -> #REF! | AI11: =VLOOKUP(A11,#REF!,40,FALSE) -> #REF!
A12: 400771524 | B12: NOBLE ENERGY INC | C12: 100322 | D12: 42018 | E12: FLOWLINE | F12: A pressure test was conducted on the flowline associated with the Victor C 29-10 well. Results indicated a loss of pressure and a leak. The area was uncovered and impacted soil above COGCC Table 910-1 standards was discovered. An excavation will be scheduled and the production equipment will remain shut in. | G12: WELD | I12: The flowline developed a leak | J12: the flowline will be repaired | K12: Unknown | L12: Unknown | M12: -104.57502 | N12: 40.279715 | O12: 0 | Q12: NULL | S12: NULL | U12: 0 | W12: 0 | Y12: NULL | AA12: NULL | AC12: =VLOOKUP(A12,'Basin Blanks Report'!$B$1:$F$222,3,FALSE) -> DENVER JULESBURG BASIN | AD12: =IF(OR(IFERROR(SEARCH("gathering",F12)>0,FALSE),IFERROR(SEARCH("gathering",I12)>0,FALSE)),"Gathering","Non-Gathering") -> Non-Gathering | AE12: Unknown | AF12: =VLOOKUP(A12,#REF!, 7, FALSE) -> #REF! | AG12: =VLOOKUP(A12,#REF!, 8, FALSE) -> #REF! | AI12: =VLOOKUP(A12,#REF!,40,FALSE) -> #REF!
A13: 400774763 | B13: OMIMEX PETROLEUM INC | C13: 66190 | D13: 42023 | E13: FLOWLINE | F13: The spill was discovered in the morning at the surface next to the meter shed. The well was shut in immediately. There was no standing water to be recovered. Water was seeped into the sand. The area of the flow line was excavated and flow line was repaired. | G13: YUMA | I13: #N/A | J13: #N/A | K13: Unknown | L13: Unknown | M13: -102.40858 | N13: 40.42344 | O13: NULL | Q13: NULL | S13: NULL | U13: NULL | W13: NULL | Y13: NULL | AA13: NULL | AC13: =VLOOKUP(A13,'Basin Blanks Report'!$B$1:$F$222,3,FALSE) -> DENVER JULESBURG BASIN | AD13: =IF(OR(IFERROR(SEARCH("gathering",F13)>0,FALSE),IFERROR(SEARCH("gathering",I13)>0,FALSE)),"Gathering","Non-Gathering") -> Non-Gathering | AE13: Unknown | AF13: =VLOOKUP(A13,#REF!, 7, FALSE) -> #REF! | AG13: =VLOOKUP(A13,#REF!, 8, FALSE) -> #REF! | AI13: =VLOOKUP(A13,#REF!,40,FALSE) -> #REF!
A14: 400775787 | B14: FOUNDATION ENERGY MANAGEMENT LLC | C14: 10112 | D14: 42023 | E14: FLOWLINE | F14: A broken valve can was discovered on the Davis Canyon pipeline, approximately 15 barrels of water was released from the line and ran about 60' down the road in front of the Columbine Springs 13C-14 location. The pumper shut-in the wells to the pipeline and constructed an earthen berm to contain the release. A vac truck was dispatched on 1/20 to vac up the fluid on the surface. | G14: RIO BLANCO | I14: #N/A | J14: #N/A | K14: Unknown | L14: Unknown | M14: -109.04637 | N14: 39.716919 | O14: 0 | Q14: 0 | S14: 15 | U14: 0 | W14: 0 | Y14: 0 | AA14: 0 | AC14: DOUGLAS CREEK ARCH | AD14: =IF(OR(IFERROR(SEARCH("gathering",F14)>0,FALSE),IFERROR(SEARCH("gathering",I14)>0,FALSE)),"Gathering","Non-Gathering") -> Non-Gathering | AE14: Unknown | AF14: =VLOOKUP(A14,#REF!, 7, FALSE) -> #REF! | AG14: =VLOOKUP(A14,#REF!, 8, FALSE) -> #REF! | AI14: =VLOOKUP(A14,#REF!,40,FALSE) -> #REF!
A15: 400777174 | B15: PIONEER NATURAL RESOURCES USA INC | C15: 10084 | D15: 42024 | E15: WATER GATHERING SYSTEM/LINE | F15: A PVC blade hit a buried water line along the edge of the road just west of the Marquez 41-32 location yesterday. A lease operator was in the area and was able to isolate the spill quickly. Approximately 1 bbl of produced water spilled out and ran east along the roadside for 75' before coming to a stop. The line has already been repaired and is back to operating normally. | G15: LAS ANIMAS | I15: A PVC blade hit a buried water line along the edge of the road | J15: The water line has been repaired and is back to operting normally. | K15: Other Outside Force Damage | L15: Line Strike | M15: -104.69052 | N15: 37.13448 | O15: 0 | Q15: 0 | S15: 1 | U15: 0 | W15: 0 | Y15: NULL | AA15: NULL | AC15: RATON BASIN | AD15: =IF(OR(IFERROR(SEARCH("gathering",F15)>0,FALSE),IFERROR(SEARCH("gathering",I15)>0,FALSE)),"Gathering","Non-Gathering") -> Non-Gathering | AE15: Unknown | AF15: =VLOOKUP(A15,#REF!, 7, FALSE) -> #REF! | AG15: =VLOOKUP(A15,#REF!, 8, FALSE) -> #REF! | AI15: =VLOOKUP(A15,#REF!,40,FALSE) -> #REF!
A16: 400778816 | B16: CRIMSON EXPLORATION OPERATING INC | C16: 10170 | D16: 42026 | E16: TANK BATTERY | F16: While conducting shallow excavation inside the tank battery berm to address a surface release (Document #s 400773673, 400777854), historical petroleum hydrocarbon impacts were encountered at approximately 6 inches below ground surface. There was no indication that any lines, tanks, or valves were leaking. All associated fittings were tight. The volume of the release is unknown. A topographic Site Location Map is provided as Figure 1. | G16: ELBERT | H16: x | I16: While conducting shallow excavation inside the tank battery berm to address a surface release (Document #s 400773673, 400777854), historical petroleum hydrocarbon impacts were encountered at approximately 6 inches below ground surface. There was no indication that any lines, tanks or valves were leaking. All associated fittings were tight. The volume of the release is unknown. | J16: The facility will be rebuilt with new piping. | K16: Unknown | L16: Unknown | M16: -104.57469 | N16: 39.51391 | O16: NULL | Q16: NULL | S16: NULL | U16: 0 | W16: 0 | Y16: NULL | AA16: NULL | AC16: DENVER JULESBURG BASIN | AD16: =IF(OR(IFERROR(SEARCH("gathering",F16)>0,FALSE),IFERROR(SEARCH("gathering",I16)>0,FALSE)),"Gathering","Non-Gathering") -> Non-Gathering | AE16: Unknown | AF16: =VLOOKUP(A16,#REF!, 7, FALSE) -> #REF! | AG16: =VLOOKUP(A16,#REF!, 8, FALSE) -> #REF! | AI16: =VLOOKUP(A16,#REF!,40,FALSE) -> #REF!
A17: 400779475 | B17: WARD PETROLEUM CORPORATION | C17: 10359 | D17: 42027 | E17: FLOWLINE | F17: Pumper noticed well had not produced for past two days, but polish rod was not hot. Walked around area and noticed spill on surface due to split in flowline. Flowline was test 1 month ago. Immediately shut well in and ordered backhoe to build temporary berm to keep spill from navigating further. Estimated 15 bbl release from pumper. Theoretical release for last two days is 8 bbl of oil. Will assess location with BLM, COGCC, and forestry service to properly remediate spill. | G17: WELD | I17: It is believed that during a routine hot oiling of the production flow line to clear it of paraffin that the hot oiler exceeded the specified maximum pressure of 80psi;This caused the flow line to split. Since the line was being cleared of paraffin, the corresponding pressure drop most likely looked like the paraffin had started moving towards the production battery, rather than leaking. | J17: Flow lines are tested yearly to determine their ability to operate. A replacement section will be added to the line and the line will be tested 80% above past tests to ensure function. | K17: Incorrect Operation | L17: Overpressure | M17: -104.521 | N17: 40.83795 | O17: 80 | Q17: 0 | S17: 0 | U17: 0 | W17: 0 | Y17: NULL | AA17: NULL | AC17: =VLOOKUP(A17,'Basin Blanks Report'!$B$1:$F$222,3,FALSE) -> DENVER JULESBURG BASIN | AD17: =IF(OR(IFERROR(SEARCH("gathering",F17)>0,FALSE),IFERROR(SEARCH("gathering",I17)>0,FALSE)),"Gathering","Non-Gathering") -> Non-Gathering | AE17: Unknown | AF17: =VLOOKUP(A17,#REF!, 7, FALSE) -> #REF! | AG17: =VLOOKUP(A17,#REF!, 8, FALSE) -> #REF! | AI17: =VLOOKUP(A17,#REF!,40,FALSE) -> #REF!
A18: 400779819 | B18: AUGUSTUS ENERGY RESOURCES LLC | C18: 10489 | D18: 42027 | E18: WELL | F18: The water line at the surface riser froze and created a small split near the Well head. Estimated between 10 & 20 bbls. No surface water to recover. Water line valve was shut off and broken pipe was replaced with a new piece of pipe. Soil samples have been taken and sent to lab for analysis and treatment will be determined on out come of analyses. The size of the line leak wsa approximately 18" and 96' long. See attached hand drawn map for details. 3 Soil samples were taken, 1 at wellhead, one east of wellhead lat 40.07738/Lon -102.54639 and one at end of affected area by lease road lat 40.07732/Lat -102.54605. | G18: YUMA | I18: #N/A | J18: #N/A | K18: Natural Force Damage | L18: Line Freeze | M18: -102.54659 | N18: 40.077328 | O18: 0 | Q18: 0 | S18: 20 | U18: 0 | W18: 0 | Y18: 0 | AA18: 0 | AC18: =VLOOKUP(A18,'Basin Blanks Report'!$B$1:$F$222,3,FALSE) -> DENVER JULESBURG BASIN | AD18: =IF(OR(IFERROR(SEARCH("gathering",F18)>0,FALSE),IFERROR(SEARCH("gathering",I18)>0,FALSE)),"Gathering","Non-Gathering") -> Non-Gathering | AE18: Unknown | AF18: =VLOOKUP(A18,#REF!, 7, FALSE) -> #REF! | AG18: =VLOOKUP(A18,#REF!, 8, FALSE) -> #REF! | AI18: =VLOOKUP(A18,#REF!,40,FALSE) -> #REF!
A19: 400781565 | B19: BAYSWATER EXPLORATION AND PRODUCTION LLC | C19: 10261 | D19: 42030 | E19: FLOWLINE | F19: A produced water release was found this morning on our Kaiser 17, 41, & 42-10 tank battery. The leak was in the dumpline in between the separator and the produced water tank. We estimate, at the most, one barrel of produced water was released. We are vacc’ing out the water from about a 26 inch diameter pot hole today. Once the water is removed, we will clean the soil and take soil samples for submittal. The pipeline will be replaced with a new pipe today or tomorrow. | G19: WELD | I19: A leak in a flowline | J19: This leaking flowline has been replaced and will no longer leak. | K19: Unknown | L19: Unknown | M19: -104.64019 | N19: 40.505964 | O19: 0 | Q19: 0 | S19: 1 | U19: 0 | W19: 0 | Y19: NULL | AA19: NULL | AC19: =VLOOKUP(A19,'Basin Blanks Report'!$B$1:$F$222,3,FALSE) -> DENVER JULESBURG BASIN | AD19: =IF(OR(IFERROR(SEARCH("gathering",F19)>0,FALSE),IFERROR(SEARCH("gathering",I19)>0,FALSE)),"Gathering","Non-Gathering") -> Non-Gathering | AE19: Unknown | AF19: =VLOOKUP(A19,#REF!, 7, FALSE) -> #REF! | AG19: =VLOOKUP(A19,#REF!, 8, FALSE) -> #REF! | AI19: =VLOOKUP(A19,#REF!,40,FALSE) -> #REF!
A20: 400782763 | B20: KERR MCGEE GATHERING LLC | C20: 47121 | D20: 42031 | E20: PIPELINE | F20: A release was discovered at the 38-0000-5569-6" pipeline when condensate was found surfacing above ground. The pipeline was immediately shut in and excavation activities commenced. Groundwater was encountered in the excavation area at approximately 20 feet below ground surface (bgs). A groundwater sample (GW01) was collected and submitted to Origins Laboratory in Denver, Colorado for analysis of benzene, toluene, ethylbenzene, and total xylenes (BTEX) by USEPA Method 8260B. Analytical results received on January 27, 2015 indicated benzene and total xylenes concentrations were in exceedance of applicable COGCC Table 910-1 groundwater standards. Groundwater analytical data is presented in the attached Table 1 and laboratory analytical report. Site investigation activities are on-going and will be summarized in a subsequent Supplemental Form 19. | G20: ADAMS | I20: Condensate was discovered surfacing on the ground above the buried pipeline. A corrosion hole in the line was discovered upon excavation activities. | J20: The production line was repaired and will be routinely tested for integrity. | K20: Corrosion | L20: Corrosion Type Unknown | M20: -104.5741 | N20: 39.9259 | O20: 0 | Q20: NULL | S20: 0 | U20: 0 | W20: 0 | Y20: NULL | AA20: NULL | AC20: DENVER JULESBURG BASIN | AD20: =IF(OR(IFERROR(SEARCH("gathering",F20)>0,FALSE),IFERROR(SEARCH("gathering",I20)>0,FALSE)),"Gathering","Non-Gathering") -> Non-Gathering | AE20: Metallic | AF20: =VLOOKUP(A20,#REF!, 7, FALSE) -> #REF! | AG20: =VLOOKUP(A20,#REF!, 8, FALSE) -> #REF! | AI20: =VLOOKUP(A20,#REF!,40,FALSE) -> #REF!
A21: 400783018 | B21: VANGUARD OPERATING LLC | C21: 10531 | D21: 42033 | E21: WELL PAD | F21: During routine maintenance activities, impacted soil was encountered on the eastern end of the tank battery. The visually impacted soil was encountered within the subsurface immediately around the dump line. A third-party consultant collected multiple samples from the excavation and these samples were sent for laboratory analysis. The excavated soils within the lined secondary containment were also sampled and analyzed. Laboratory results indicated that all four sidewall samples were compliant with Table 910-1 Concentration Levels except for the samples collected from the base of the excavation and from the spoils pile. Both of these samples exceeded the Concentration Levels for TPH. Excavation activities continued to identify the vertical extent of of the TPH impact and additional samples were collected. These analytical results are pending and additonal information will be provided in a supplemental submittal. | G21: GARFIELD | H21: x | I21: During routine maintenance activities, impacted soil was encountered at the eastern end of the tank battery. Visually impacted soil was encountered within the subsurface immediately around the dump line. Potential corrosion issues with the dump line are likely the cause of the historic impacts. The 2014 pressure test data for this facility has been included as an attachment at the direction of COGCC staff. | J21: All dump lines will be replaced as a precautionary measure and sacrificial anodes will be installed on all new lines to address any potential corrosion issues in the future. | K21: Corrosion | L21: Corrosion Type Unknown | M21: -107.58246 | N21: 39.483291 | O21: 0 | Q21: NULL | S21: NULL | U21: 0 | W21: 0 | Y21: NULL | AA21: NULL | AC21: PICEANCE BASIN | AD21: =IF(OR(IFERROR(SEARCH("gathering",F21)>0,FALSE),IFERROR(SEARCH("gathering",I21)>0,FALSE)),"Gathering","Non-Gathering") -> Non-Gathering | AE21: Metallic | AF21: =VLOOKUP(A21,#REF!, 7, FALSE) -> #REF! | AG21: =VLOOKUP(A21,#REF!, 8, FALSE) -> #REF! | AI21: =VLOOKUP(A21,#REF!,40,FALSE) -> #REF!
A22: 400784214 | B22: FOUNDATION ENERGY MANAGEMENT LLC | C22: 10112 | D22: 42033 | E22: FLOWLINE | F22: Turned well back to production after a flowline repair and remediation project East of the Sooner 13-16 wellpad. Pumper returned to location the next day to discover a new flowline leak that had released approximately 2 bbls of water. A vac truck was dispatched immediately to vac up the fluids on the surface and a crew will be digging down to the flowline to determine cause of leak, repair and remediate contaminated soil per COGCC regs. | G22: WELD | I22: Flowline leaked after initial repair and test. Working to repair and re-test before turning the well back online. | J22: Frequently testing our flowlines to ensure no leaks or corrosion. | K22: Unknown | L22: Unknown | M22: -103.87093 | N22: 40.65633 | O22: 0 | Q22: 0 | S22: 2 | U22: 0 | W22: 0 | Y22: NULL | AA22: NULL | AC22: =VLOOKUP(A22,'Basin Blanks Report'!$B$1:$F$222,3,FALSE) -> DENVER JULESBURG BASIN | AD22: =IF(OR(IFERROR(SEARCH("gathering",F22)>0,FALSE),IFERROR(SEARCH("gathering",I22)>0,FALSE)),"Gathering","Non-Gathering") -> Non-Gathering | AE22: Unknown | AF22: =VLOOKUP(A22,#REF!, 7, FALSE) -> #REF! | AG22: =VLOOKUP(A22,#REF!, 8, FALSE) -> #REF! | AI22: =VLOOKUP(A22,#REF!,40,FALSE) -> #REF!
A23: 400785370 | B23: DCP MIDSTREAM LP | C23: 4680 | D23: 42037 | E23: GAS GATHERING SYSTEM | F23: A release originating from an underground pipeline occured on the Tampa Compressor Station owned by DCP Midstream. The release has believed to have been stopped and soil remediation activities have begun. An investigation is underway as to what may have caused the initial release. More information will be provided on the 10 day follow-up report. | G23: WELD | I23: #N/A | J23: #N/A | K23: Unknown | L23: Unknown | M23: -104.48 | N23: 40.18 | O23: NULL | Q23: NULL | S23: 0 | U23: 0 | W23: 0 | Y23: NULL | AA23: NULL | AC23: =VLOOKUP(A23,'Basin Blanks Report'!$B$1:$F$222,3,FALSE) -> DENVER JULESBURG BASIN | AD23: =IF(OR(IFERROR(SEARCH("gathering",F23)>0,FALSE),IFERROR(SEARCH("gathering",I23)>0,FALSE)),"Gathering","Non-Gathering") -> Non-Gathering | AE23: Unknown | AF23: =VLOOKUP(A23,#REF!, 7, FALSE) -> #REF! | AG23: =VLOOKUP(A23,#REF!, 8, FALSE) -> #REF! | AI23: =VLOOKUP(A23,#REF!,40,FALSE) -> #REF!
A24: 400785554 | B24: DCP MIDSTREAM LP | C24: 4680 | D24: 42037 | E24: PIPELINE | F24: On February 2, 2015 DCP was notified about a potential underground pipeline release located 1/4 mile southwest of the intersection of CR 18 and CR 21. Upon investigation it was determined that DCP had a 2'' field gathering line that was leaking. The liquids in the line were removed via vacuum truck. Current repair activities and remediation plans are being scheduled. The leak has stopped and no impacts to groundwater have been identifed at this time. | G24: WELD | I24: #N/A | J24: #N/A | K24: Unknown | L24: Unknown | M24: -104.872 | N24: 40.113 | O24: NULL | Q24: NULL | S24: NULL | U24: NULL | W24: NULL | Y24: NULL | AA24: NULL | AC24: =VLOOKUP(A24,'Basin Blanks Report'!$B$1:$F$222,3,FALSE) -> DENVER JULESBURG BASIN | AD24: =IF(OR(IFERROR(SEARCH("gathering",F24)>0,FALSE),IFERROR(SEARCH("gathering",I24)>0,FALSE)),"Gathering","Non-Gathering") -> Gathering | AE24: Unknown | AF24: =VLOOKUP(A24,#REF!, 7, FALSE) -> #REF! | AG24: =VLOOKUP(A24,#REF!, 8, FALSE) -> #REF! | AI24: =VLOOKUP(A24,#REF!,40,FALSE) -> #REF!
A25: 400786064 | B25: K P KAUFFMAN COMPANY INC | C25: 46290 | D25: 42038 | E25: FLOWLINE | F25: This is to notify of a 3 bbl oil and water spill that was discovered yesterday, February 3, 2015. At about 16:00 Encana notified K.P. Kauffman Company, Inc. (KPK) of a leak in or near Encana's dry retention pond. The leak appears to come from a pipe that Encana cut while building the retention pond. It was caused by a valve failure isolating the consolidation line and the cut line. Since the spill took place within Encana's fenced area, KPK was denied access to start cleanup; however, immediately upon discovery of the spill, Encana started digging out the contaminated soil and determined the extent of the contamination with visual inspection. KPK has now been granted access to the location and will take over the remediation operations. Based on flowline volumes and well production, it is estimated that 3 bbl of oil and produced water were spilled. | G25: WELD | I25: The leak appears to come from a pipe that Encana cut while building the retention pond. It was caused by a valve failure isolating the consolidation line and the cut line. | J25: Following proper repairs to the damged flowline, the excavated area will be filled in with clean fill dirt. A new flow line outside the retention pond will be installed. | K25: Excavation Force Damage | L25: Line Strike | M25: -104.88918 | N25: 40.01888 | O25: 1 | Q25: 0 | S25: 1 | U25: 0 | W25: 0 | Y25: NULL | AA25: NULL | AC25: =VLOOKUP(A25,'Basin Blanks Report'!$B$1:$F$222,3,FALSE) -> DENVER JULESBURG BASIN | AD25: =IF(OR(IFERROR(SEARCH("gathering",F25)>0,FALSE),IFERROR(SEARCH("gathering",I25)>0,FALSE)),"Gathering","Non-Gathering") -> Non-Gathering | AE25: Unknown | AF25: =VLOOKUP(A25,#REF!, 7, FALSE) -> #REF! | AG25: =VLOOKUP(A25,#REF!, 8, FALSE) -> #REF! | AI25: =VLOOKUP(A25,#REF!,40,FALSE) -> #REF!
A26: 400786068 | B26: AUGUSTUS ENERGY RESOURCES LLC | C26: 10489 | D26: 42038 | E26: FLOWLINE | F26: the Poly pipe fuse broke, valves where shut to isolate the water, no surface water to recover, poly fuse was repaired. Size of area was approx 5' x 5'. Soil samples have been taken and will be submitted on a supplemental form 19 when received. As soon as analyses are received they will be reviewed and treated per the lab recommendations. The location will be strawed to help hold the moisture. | G26: YUMA | I26: #N/A | J26: #N/A | K26: Pipe, Weld, or Joint Failure | L26: Poly Fitting or Fuse Failure | M26: -102.407 | N26: 39.991201 | O26: 0 | Q26: 0 | S26: 15 | U26: 0 | W26: 0 | Y26: NULL | AA26: NULL | AC26: =VLOOKUP(A26,'Basin Blanks Report'!$B$1:$F$222,3,FALSE) -> DENVER JULESBURG BASIN | AD26: =IF(OR(IFERROR(SEARCH("gathering",F26)>0,FALSE),IFERROR(SEARCH("gathering",I26)>0,FALSE)),"Gathering","Non-Gathering") -> Non-Gathering | AE26: Non-Metallic | AF26: =VLOOKUP(A26,#REF!, 7, FALSE) -> #REF! | AG26: =VLOOKUP(A26,#REF!, 8, FALSE) -> #REF! | AI26: =VLOOKUP(A26,#REF!,40,FALSE) -> #REF!
A27: 400786811 | B27: GREAT WESTERN OPERATING COMPANY LLC | C27: 10110 | D27: 42038 | E27: TANK BATTERY | F27: 915 pm Tues 02.03.15 a leak from a subsurface poly collector line was identified. All wells had been shut in for well mitigations in the area so there was minimal pressure on the line. Approximately 2 bbls of produced water with a skim of hydrocarbons was removed from the hole created by the leak. Some liquid did migrate down the road and this was all picked up also. | G27: WELD | I27: Subsurface collector line rupture. | J27: Approximately 2 barrels of produced water were removed from the hole created by the leak and the ruptured collector line was repaired. | K27: Unknown | L27: Unknown | M27: -104.88052 | N27: 40.493953 | O27: 0 | Q27: 0 | S27: 2 | U27: 0 | W27: 0 | Y27: NULL | AA27: NULL | AC27: =VLOOKUP(A27,'Basin Blanks Report'!$B$1:$F$222,3,FALSE) -> DENVER JULESBURG BASIN | AD27: =IF(OR(IFERROR(SEARCH("gathering",F27)>0,FALSE),IFERROR(SEARCH("gathering",I27)>0,FALSE)),"Gathering","Non-Gathering") -> Non-Gathering | AE27: Non-Metallic | AF27: =VLOOKUP(A27,#REF!, 7, FALSE) -> #REF! | AG27: =VLOOKUP(A27,#REF!, 8, FALSE) -> #REF! | AI27: =VLOOKUP(A27,#REF!,40,FALSE) -> #REF!
A28: 400786818 | B28: KERR MCGEE OIL & GAS ONSHORE LP | C28: 47120 | D28: 42038 | E28: TANK BATTERY | F28: During deconstruction activities at the HSR-Charlene 2-36 tank battery, historical petroleum hydrocarbon impacts were encountered beneath the produced water sump. There was no indication that the dump lines or the produced water tank were leaking. The volume of the release is unknown. Confirmation soil and groundwater samples were collected from the excavation and the analytical results and excavation details are provided below. A topographic Site Location Map showing the general location of the release is attached as Figure 1. | G28: WELD | H28: x | I28: During deconstruction activities at the HSR-Charlene 2-36 tank battery, historical petroleum hydrocarbon impacts were encountered beneath the produced water sump. There was no indication that the dump lines or the produced water tank were leaking. The volume of the release is unknown. | J28: The tank battery was removed and the site was restored to it's pre-release grade. | K28: Unknown | L28: Unknown | M28: -104.83497 | N28: 40.182715 | O28: NULL | Q28: 0 | S28: NULL | U28: 0 | W28: 0 | Y28: NULL | AA28: NULL | AC28: =VLOOKUP(A28,'Basin Blanks Report'!$B$1:$F$222,3,FALSE) -> DENVER JULESBURG BASIN | AD28: =IF(OR(IFERROR(SEARCH("gathering",F28)>0,FALSE),IFERROR(SEARCH("gathering",I28)>0,FALSE)),"Gathering","Non-Gathering") -> Non-Gathering | AE28: Unknown | AF28: =VLOOKUP(A28,#REF!, 7, FALSE) -> #REF! | AG28: =VLOOKUP(A28,#REF!, 8, FALSE) -> #REF! | AI28: =VLOOKUP(A28,#REF!,40,FALSE) -> #REF!
A29: 400787201 | B29: PIONEER NATURAL RESOURCES USA INC | C29: 10084 | D29: 42038 | E29: WATER GATHERING SYSTEM/LINE | F29: Gas buster on the SE corner of location froze and broke, allowing approximately 10 bbls of produced water to pool on location. Some water ran south off location and skirted along the toe of the hillside until coming to a stop in an open grassy area. The spill was isolated upon discovery and repairs are being done to the gas buster and water line. | G29: LAS ANIMAS | I29: Gas buster on the SE corner of location froze and broke | J29: Gas buster and valve has been replaced and things are operating normally | K29: Natural Force Damage | L29: Valve Freeze | M29: -104.79961 | N29: 37.21143 | O29: 0 | Q29: 0 | S29: 10 | U29: 0 | W29: 0 | Y29: NULL | AA29: NULL | AC29: RATON BASIN | AD29: =IF(OR(IFERROR(SEARCH("gathering",F29)>0,FALSE),IFERROR(SEARCH("gathering",I29)>0,FALSE)),"Gathering","Non-Gathering") -> Non-Gathering | AE29: Unknown | AF29: =VLOOKUP(A29,#REF!, 7, FALSE) -> #REF! | AG29: =VLOOKUP(A29,#REF!, 8, FALSE) -> #REF! | AI29: =VLOOKUP(A29,#REF!,40,FALSE) -> #REF!
A30: 400787752 | B30: NOBLE ENERGY INC | C30: 100322 | D30: 42039 | E30: FLOWLINE | F30: The flow line was pressure tested and a leak was discovered 30 feet from the well head. All production equipment is shut in and an excavation is scheduled. | G30: WELD | I30: During a pressure test of the flowline a section lost pressure | J30: The flowline will be repaired or replaced. | K30: Unknown | L30: Unknown | M30: -104.5164 | N30: 40.27758 | O30: 0 | Q30: NULL | S30: NULL | U30: 0 | W30: 0 | Y30: NULL | AA30: NULL | AC30: =VLOOKUP(A30,'Basin Blanks Report'!$B$1:$F$222,3,FALSE) -> DENVER JULESBURG BASIN | AD30: =IF(OR(IFERROR(SEARCH("gathering",F30)>0,FALSE),IFERROR(SEARCH("gathering",I30)>0,FALSE)),"Gathering","Non-Gathering") -> Non-Gathering | AE30: Unknown | AF30: =VLOOKUP(A30,#REF!, 7, FALSE) -> #REF! | AG30: =VLOOKUP(A30,#REF!, 8, FALSE) -> #REF! | AI30: =VLOOKUP(A30,#REF!,40,FALSE) -> #REF!
A31: 400788049 | B31: AUGUSTUS ENERGY RESOURCES LLC | C31: 10489 | D31: 42041 | E31: WELL | F31: Poly pipe broke, we believe it was caused by freezing and thawing as there was approx. a 3" split in the pipe. We removed and replaced the broken piece. The valve was shut to isolate the water, there was no surface water to recover. Estimated bbls is 10-12. The approx. dimension of the affected area is 20' by 30', 2 spots were sampled as well as a background area and the samples have been submitted for testing. A supplemental form 19 will be submitted with soil analyses. | G31: YUMA | I31: #N/A | J31: #N/A | K31: Natural Force Damage | L31: Line Freeze | M31: -102.49659 | N31: 40.28889 | O31: 0 | Q31: 0 | S31: 12 | U31: 0 | W31: 0 | Y31: 0 | AA31: 0 | AC31: =VLOOKUP(A31,'Basin Blanks Report'!$B$1:$F$222,3,FALSE) -> DENVER JULESBURG BASIN | AD31: =IF(OR(IFERROR(SEARCH("gathering",F31)>0,FALSE),IFERROR(SEARCH("gathering",I31)>0,FALSE)),"Gathering","Non-Gathering") -> Non-Gathering | AE31: Non-Metallic | AF31: =VLOOKUP(A31,#REF!, 7, FALSE) -> #REF! | AG31: =VLOOKUP(A31,#REF!, 8, FALSE) -> #REF! | AI31: =VLOOKUP(A31,#REF!,40,FALSE) -> #REF!
A32: 400788096 | B32: AUGUSTUS ENERGY RESOURCES LLC | C32: 10489 | D32: 42041 | E32: WELL | F32: It appears the fuse in the poly pipe broke. The valves were shut to isolate the water. An Electra fuse was used to repair/replace the broken fuse. The size of the affected area is approx. 132' long and 12' wide. 2 Soil samples were taken from the affected area and 1 from the background. Soil Analyses will be submitted on a Supplemental form 19 and we will reclaim the area based on the recommendations supplied with the Analyses. | G32: YUMA | I32: #N/A | J32: #N/A | K32: Pipe, Weld, or Joint Failure | L32: Poly Fitting or Fuse Failure | M32: -102.27949 | N32: 39.93369 | O32: NULL | Q32: NULL | S32: NULL | U32: NULL | W32: NULL | Y32: NULL | AA32: NULL | AC32: DENVER JULESBURG BASIN | AD32: =IF(OR(IFERROR(SEARCH("gathering",F32)>0,FALSE),IFERROR(SEARCH("gathering",I32)>0,FALSE)),"Gathering","Non-Gathering") -> Non-Gathering | AE32: Non-Metallic | AF32: =VLOOKUP(A32,#REF!, 7, FALSE) -> #REF! | AG32: =VLOOKUP(A32,#REF!, 8, FALSE) -> #REF! | AI32: =VLOOKUP(A32,#REF!,40,FALSE) -> #REF!
A33: 400789484 | B33: CHEVRON USA INC | C33: 16700 | D33: 42044 | E33: FLOWLINE | F33: Monday (02-09-2015) at approximately 9:46 AM a produced water leak occurred on the lateral injection line to AC McLaughlin 93. Approximately 112.9 BBLs of produced water was released. The lateral valve was shut in immediately upon detection. Vacuum truck recovered an estimated 100 BBLs. The affected area has been water washed and soil samples will be taken. Water ran into a dry erosion channel. | G33: RIO BLANCO | I33: #N/A | J33: #N/A | K33: Unknown | L33: Unknown | M33: -108.9118 | N33: 40.1484 | O33: NULL | Q33: NULL | S33: 112.9 | U33: NULL | W33: NULL | Y33: NULL | AA33: NULL | AC33: PICEANCE BASIN | AD33: =IF(OR(IFERROR(SEARCH("gathering",F33)>0,FALSE),IFERROR(SEARCH("gathering",I33)>0,FALSE)),"Gathering","Non-Gathering") -> Non-Gathering | AE33: Unknown | AF33: =VLOOKUP(A33,#REF!, 7, FALSE) -> #REF! | AG33: =VLOOKUP(A33,#REF!, 8, FALSE) -> #REF! | AI33: =VLOOKUP(A33,#REF!,40,FALSE) -> #REF!
A34: 400790938 | B34: BAYSWATER EXPLORATION AND PRODUCTION LLC | C34: 10261 | D34: 42046 | E34: FLOWLINE | F34: Due to an inspection notice on the Causey 17 Wellhead indicating that stained soil existed and needed to be remediated, our foreman started the clean up and found a larger area of contamination. He believes that some of this contamination is historical, and some is recent from a probable flowline leak. He is currently investigating the cause of the leak and excavating the area to determine the extent of the contamination. | G34: ADAMS | I34: Leak in the flowline | J34: Older flowlines were removed. Current working flowline was vacc'ed out and pressure tested (see attached) Connectors were also replaced. | K34: Unknown | L34: Unknown | M34: -103.7466 | N34: 39.859699 | O34: 10 | Q34: 0 | S34: 200 | U34: 0 | W34: 0 | Y34: NULL | AA34: NULL | AC34: DENVER JULESBURG BASIN | AD34: =IF(OR(IFERROR(SEARCH("gathering",F34)>0,FALSE),IFERROR(SEARCH("gathering",I34)>0,FALSE)),"Gathering","Non-Gathering") -> Non-Gathering | AE34: Unknown | AF34: =VLOOKUP(A34,#REF!, 7, FALSE) -> #REF! | AG34: =VLOOKUP(A34,#REF!, 8, FALSE) -> #REF! | AI34: =VLOOKUP(A34,#REF!,40,FALSE) -> #REF!
A35: 400791362 | B35: PDC ENERGY INC | C35: 69175 | D35: 42046 | E35: TANK BATTERY | F35: While completing construction activities at the Maxey 2, 33, 43, 44-24, 24D facility, historical impacts were encountered in the area of a flowline. Based on field interpretations, it appears that groundwater impacts are present. Confirmation soil and groundwater samples will be collected. | G35: WELD | H35: x | I35: Historic impacts were discovered during construction activities. | J35: The flow line was replaced and will be routinely pressure tested. | K35: Unknown | L35: Unknown | M35: -104.605 | N35: 40.378526 | O35: NULL | Q35: 0 | S35: 0 | U35: 0 | W35: 0 | Y35: NULL | AA35: NULL | AC35: =VLOOKUP(A35,'Basin Blanks Report'!$B$1:$F$222,3,FALSE) -> DENVER JULESBURG BASIN | AD35: =IF(OR(IFERROR(SEARCH("gathering",F35)>0,FALSE),IFERROR(SEARCH("gathering",I35)>0,FALSE)),"Gathering","Non-Gathering") -> Non-Gathering | AE35: Unknown | AF35: =VLOOKUP(A35,#REF!, 7, FALSE) -> #REF! | AG35: =VLOOKUP(A35,#REF!, 8, FALSE) -> #REF! | AI35: =VLOOKUP(A35,#REF!,40,FALSE) -> #REF!
A36: 400792553 | B36: KERR MCGEE OIL & GAS ONSHORE LP | C36: 47120 | D36: 42047 | E36: TANK BATTERY | F36: A release was discovered below the dump lines during battery reconstruction activities at the Wierman 43-7 (1) production facility. Approximately 20 cubic yards of impacted material were removed and transported to the Buffalo Ridge Landfill in Keenesburg, Colorado for disposal. Groundwater was encountered in the excavation area at approximately 3.5 feet below ground surface (bgs). A groundwater sample (GW01) was collected and submitted to Origins Laboratory in Denver, Colorado for analysis of benzene, toluene, ethylbenzene, and total xylenes (BTEX) by USEPA Method 8260B. Analytical results received on February 13, 2015 indicated benzene concentrations were in exceedance of applicable COGCC Table 910-1 standards. Excavation activities are on-going at this location and will be summarized in a subsequent Supplemental Form 19. | G36: ADAMS | H36: x | I36: During the replacement of the tank battery, hydrocarbon impacts were discovered along the dump line. | J36: The battery will be rebuilt with a geosynthetic liner, a poly drain line, and a double walled fiberglass produced water tank. | K36: Unknown | L36: Unknown | M36: -104.92609 | N36: 39.975673 | O36: 0 | Q36: NULL | S36: NULL | U36: 0 | W36: 0 | Y36: NULL | AA36: NULL | AC36: DENVER JULESBURG BASIN | AD36: =IF(OR(IFERROR(SEARCH("gathering",F36)>0,FALSE),IFERROR(SEARCH("gathering",I36)>0,FALSE)),"Gathering","Non-Gathering") -> Non-Gathering | AE36: Unknown | AF36: =VLOOKUP(A36,#REF!, 7, FALSE) -> #REF! | AG36: =VLOOKUP(A36,#REF!, 8, FALSE) -> #REF! | AI36: =VLOOKUP(A36,#REF!,40,FALSE) -> #REF!
A37: 400792604 | B37: NOBLE ENERGY INC | C37: 100322 | D37: 42048 | E37: TANK BATTERY | F37: Pipe on water vault malfunctioned and 69 bbls of produced water was unintentionally released. Malfunction is currently under investigation. 7bbls were recovered while 62 bbls were released to ground surface. A 3rd party environmental consultant was called to assess the impacts outside of the berm area. Production equipment has been shut in. | G37: WELD | I37: The produced water line malfunctioned and will be repaired and tested prior to being put back into production. | J37: The produced water line will be repaired | K37: Unknown | L37: Unknown | M37: -104.51987 | N37: 40.341168 | O37: 0 | Q37: 0 | S37: 69 | U37: 0 | W37: 0 | Y37: NULL | AA37: NULL | AC37: =VLOOKUP(A37,'Basin Blanks Report'!$B$1:$F$222,3,FALSE) -> DENVER JULESBURG BASIN | AD37: =IF(OR(IFERROR(SEARCH("gathering",F37)>0,FALSE),IFERROR(SEARCH("gathering",I37)>0,FALSE)),"Gathering","Non-Gathering") -> Non-Gathering | AE37: Unknown | AF37: =VLOOKUP(A37,#REF!, 7, FALSE) -> #REF! | AG37: =VLOOKUP(A37,#REF!, 8, FALSE) -> #REF! | AI37: =VLOOKUP(A37,#REF!,40,FALSE) -> #REF!
A38: 400795311 | B38: NOBLE ENERGY INC | C38: 100322 | D38: 42053 | E38: TANK BATTERY | F38: The produced water line malfunctioned releasing 20 gallons of produced water to the groundsurface inside containment and an undetermined amount of produced water below groundsurface. All production equipment has been shut in and a hydroexcavator is on location uncovering the flow lines. Remediation options are being evaluated. Site Location: Sauer Econode F33 | G38: WELD | I38: The produced water line leading to the produced water vault from the separator developed a leak. The portion of the line will be cut and replaced. A pressure test will be conducted to ensure the repaired section holds pressure. | J38: The portinon of the line will be repaired. | K38: Unknown | L38: Unknown | M38: -104.67337 | N38: 40.351023 | O38: 0 | Q38: 0 | S38: NULL | U38: 0 | W38: 0 | Y38: NULL | AA38: NULL | AC38: =VLOOKUP(A38,'Basin Blanks Report'!$B$1:$F$222,3,FALSE) -> DENVER JULESBURG BASIN | AD38: =IF(OR(IFERROR(SEARCH("gathering",F38)>0,FALSE),IFERROR(SEARCH("gathering",I38)>0,FALSE)),"Gathering","Non-Gathering") -> Non-Gathering | AE38: Unknown | AF38: =VLOOKUP(A38,#REF!, 7, FALSE) -> #REF! | AG38: =VLOOKUP(A38,#REF!, 8, FALSE) -> #REF! | AI38: =VLOOKUP(A38,#REF!,40,FALSE) -> #REF!
A39: 400795533 | B39: AUGUSTUS ENERGY RESOURCES LLC | C39: 10489 | D39: 42053 | E39: FLOWLINE | F39: Bad Poly Fuse broke, isolation valves were shut. There was no surface water, but we did have a vac truck suck the water from the line. Poly fuse was repaired. Size of affected area was aprox. 38' long x 6' wide. Soil samples were taken and have been sent to lab for analysis. The area will be treated with Pelleted Grade gypsum, straw will be stitched to prevent erosion and depending on the soil analysis results will determine when area will be re-seeded. | G39: YUMA | I39: #N/A | J39: #N/A | K39: Pipe, Weld, or Joint Failure | L39: Poly Fitting or Fuse Failure | M39: -102.47744 | N39: 40.00284 | O39: NULL | Q39: NULL | S39: NULL | U39: NULL | W39: NULL | Y39: NULL | AA39: NULL | AC39: =VLOOKUP(A39,'Basin Blanks Report'!$B$1:$F$222,3,FALSE) -> DENVER JULESBURG BASIN | AD39: =IF(OR(IFERROR(SEARCH("gathering",F39)>0,FALSE),IFERROR(SEARCH("gathering",I39)>0,FALSE)),"Gathering","Non-Gathering") -> Non-Gathering | AE39: Non-Metallic | AF39: =VLOOKUP(A39,#REF!, 7, FALSE) -> #REF! | AG39: =VLOOKUP(A39,#REF!, 8, FALSE) -> #REF! | AI39: =VLOOKUP(A39,#REF!,40,FALSE) -> #REF!
A40: 400802279 | B40: PIONEER NATURAL RESOURCES USA INC | C40: 10084 | D40: 42064 | E40: WATER GATHERING SYSTEM/LINE | F40: Above ground water gathering line had a small split in it next to the meter house. Approximately 1 bbl of produced water sprayed out on location and melted snow in the spray area. No water left location. The well was shut off upon discovery and will be restarted after repairs to the line have been completed. | G40: LAS ANIMAS | I40: Above ground water gathering line froze and split next to the meter house. Approximately 1 bbl of produced water sprayed out on location and melted snow in the spray area. No water left location. | J40: The line has been repaired and the well is operating normally. | K40: Natural Force Damage | L40: Line Freeze | M40: -104.89455 | N40: 37.17172 | O40: 0 | Q40: 0 | S40: 1 | U40: 0 | W40: 0 | Y40: NULL | AA40: NULL | AC40: RATON BASIN | AD40: =IF(OR(IFERROR(SEARCH("gathering",F40)>0,FALSE),IFERROR(SEARCH("gathering",I40)>0,FALSE)),"Gathering","Non-Gathering") -> Gathering | AE40: Unknown | AF40: =VLOOKUP(A40,#REF!, 7, FALSE) -> #REF! | AG40: =VLOOKUP(A40,#REF!, 8, FALSE) -> #REF! | AI40: =VLOOKUP(A40,#REF!,40,FALSE) -> #REF!
A41: 400802002 | B41: MULL DRILLING COMPANY INC | C41: 61250 | D41: 42065 | E41: FLOWLINE | F41: What happened: Flowline failed. How it was stopped: Affected well was shut in. Snow/Spilled Fluids were pushed into berm area. Fresh water was heated to recover all free fluids. Recovered: Ten barrel of crude oil -- trucked to MUSF SWD holding tank stock tank. Other: Affected flowline - will be repaired/replaced as needed and then MIT'ed. Stained soils will be washed with fresh water - all recovered fluids from wash up will be trucked to MUSF SWD holding tank. | G41: CHEYENNE | I41: #N/A | J41: #N/A | K41: Unknown | L41: Unknown | M41: -102.90285 | N41: 38.86013 | O41: 15 | Q41: 0 | S41: 0 | U41: 0 | W41: 0 | Y41: NULL | AA41: NULL | AC41: INTERBASIN AREA | AD41: =IF(OR(IFERROR(SEARCH("gathering",F41)>0,FALSE),IFERROR(SEARCH("gathering",I41)>0,FALSE)),"Gathering","Non-Gathering") -> Non-Gathering | AE41: Unknown | AF41: =VLOOKUP(A41,#REF!, 7, FALSE) -> #REF! | AG41: =VLOOKUP(A41,#REF!, 8, FALSE) -> #REF! | AI41: =VLOOKUP(A41,#REF!,40,FALSE) -> #REF!
A42: 400802314 | B42: NOBLE ENERGY INC | C42: 100322 | D42: 42065 | E42: TANK BATTERY | F42: A corrosive hole formed in the produced water line. The produced water surfaced, all production equipment was shut in and an excavation of impacted soil was initiated. Soil confirmation sampling will be collected by a third party environmental consultant. | G42: WELD | I42: The produced water line developed a hole leading from the separator to the tank battery. | J42: The section of the produced water line will be replaced. A pressure test will be conducted prior to turning the production equipment on. | K42: Corrosion | L42: Corrosion Type Unknown | M42: -104.44722 | N42: 40.514723 | O42: 0 | Q42: 0 | S42: NULL | U42: 0 | W42: 0 | Y42: NULL | AA42: NULL | AC42: =VLOOKUP(A42,'Basin Blanks Report'!$B$1:$F$222,3,FALSE) -> DENVER JULESBURG BASIN | AD42: =IF(OR(IFERROR(SEARCH("gathering",F42)>0,FALSE),IFERROR(SEARCH("gathering",I42)>0,FALSE)),"Gathering","Non-Gathering") -> Non-Gathering | AE42: Metallic | AF42: =VLOOKUP(A42,#REF!, 7, FALSE) -> #REF! | AG42: =VLOOKUP(A42,#REF!, 8, FALSE) -> #REF! | AI42: =VLOOKUP(A42,#REF!,40,FALSE) -> #REF!
A43: 400802484 | B43: NOBLE ENERGY INC | C43: 100322 | D43: 42065 | E43: TANK BATTERY | F43: During production activities the produced water line running from the tank battery to the separator developed a leak and surfaced. The production equipment was shut in and the flow line was uncovered. Remediation options are being evaluated. | G43: WELD | I43: The produced water line developed a leak | J43: The section will be replaced and pressure tested to ensure it has been repaired. | K43: Unknown | L43: Unknown | M43: -104.3553 | N43: 40.4578 | O43: 0 | Q43: 0 | S43: NULL | U43: 0 | W43: 0 | Y43: NULL | AA43: NULL | AC43: =VLOOKUP(A43,'Basin Blanks Report'!$B$1:$F$222,3,FALSE) -> DENVER JULESBURG BASIN | AD43: =IF(OR(IFERROR(SEARCH("gathering",F43)>0,FALSE),IFERROR(SEARCH("gathering",I43)>0,FALSE)),"Gathering","Non-Gathering") -> Non-Gathering | AE43: Unknown | AF43: =VLOOKUP(A43,#REF!, 7, FALSE) -> #REF! | AG43: =VLOOKUP(A43,#REF!, 8, FALSE) -> #REF! | AI43: =VLOOKUP(A43,#REF!,40,FALSE) -> #REF!
A44: 400804447 | B44: CHEVRON USA INC | C44: 16700 | D44: 42068 | E44: FLOWLINE | F44: On 11/26/2013 at approximately 10:42AM a water leak occurred on a 3” steel cement lined injection line. Approximately 162.89 BBLs of brine water and 0 BBLs of oil were released. The line was shut in immediately upon detection. Vacuum trucks removed all of the free fluid; estimated recovery is approximately 160 BBLs of brine water was recovered. The fluids that were picked up were taken to the truck unloading facility at the Main Water Plant for recycling. Soil samples will be taken. | G44: RIO BLANCO | I44: #N/A | J44: #N/A | K44: Unknown | L44: Unknown | M44: -108.84091 | N44: 40.11526 | O44: 0 | Q44: 0 | S44: 162.89 | U44: 0 | W44: 0 | Y44: 0 | AA44: 0 | AC44: PICEANCE BASIN | AD44: =IF(OR(IFERROR(SEARCH("gathering",F44)>0,FALSE),IFERROR(SEARCH("gathering",I44)>0,FALSE)),"Gathering","Non-Gathering") -> Non-Gathering | AE44: Metallic | AF44: =VLOOKUP(A44,#REF!, 7, FALSE) -> #REF! | AG44: =VLOOKUP(A44,#REF!, 8, FALSE) -> #REF! | AI44: =VLOOKUP(A44,#REF!,40,FALSE) -> #REF!
A45: 400805034 | B45: BOPCO LP | C45: 10172 | D45: 42068 | E45: FLOWLINE | F45: Flowline rupture discovered 3/5/15 at 12:00. Exact location is being investigated however the water leg that leaked has been isolated from the rest of the field. The rest of the water piping system was pressured up and tested. The water leg from the YCF 3-45 remains shut in and isolated. Approximate 416 bbls produced water was release, but due to frost/snow on ground, the water has not been identifed yet. Plans to inject air through line to identify exact location of the leak are in progress. | G45: RIO BLANCO | I45: An employee closed the SWD flowline valve at the YCF 4-32 SW Tank Battery location; causing the line to pressure up and rupture at the edge of the YCF 3-45-1 location. | J45: Re-train all personal in proceedure to transfer produced water to the disposal wells. | K45: Incorrect Operation | L45: Valve Misalignment | M45: -108.37075 | N45: 39.99114 | O45: 0 | Q45: 0 | S45: 5 | U45: 0 | W45: 0 | Y45: NULL | AA45: NULL | AC45: =VLOOKUP(A45,'Basin Blanks Report'!$B$1:$F$222,3,FALSE) -> PICEANCE BASIN | AD45: =IF(OR(IFERROR(SEARCH("gathering",F45)>0,FALSE),IFERROR(SEARCH("gathering",I45)>0,FALSE)),"Gathering","Non-Gathering") -> Non-Gathering | AE45: Unknown | AF45: =VLOOKUP(A45,#REF!, 7, FALSE) -> #REF! | AG45: =VLOOKUP(A45,#REF!, 8, FALSE) -> #REF! | AI45: =VLOOKUP(A45,#REF!,40,FALSE) -> #REF!
A46: 400805806 | B46: AUGUSTUS ENERGY RESOURCES LLC | C46: 10489 | D46: 42069 | E46: WELL | F46: The hammer union was loose, Field supervisor feels the constant change in cold/warm weather caused the union to become loose. The hammer union was tightened. There was no surface water. Lines were shut in to prevent more water from leaking until problem was found. Aprox. size of spill area is 40' wide by 50' long. Soil samples have been taken and will be sent to the lab today. Will submit analytical on a supplemental Form 19 as soon as received. The area has been treated with Agricultural grade pelleted gypsum. Location will be monitored for re-growth, erosion and weeds. We will periodically check the EC levels and when we feel the gypsum has started to activate another soil sample will be taken to access the levels and will treat accordingly to the analysis results. | G46: YUMA | I46: #N/A | J46: #N/A | K46: Incorrect Operation | L46: Improper Installation | M46: -102.6074 | N46: 40.26674 | O46: NULL | Q46: NULL | S46: NULL | U46: NULL | W46: NULL | Y46: NULL | AA46: NULL | AC46: =VLOOKUP(A46,'Basin Blanks Report'!$B$1:$F$222,3,FALSE) -> DENVER JULESBURG BASIN | AD46: =IF(OR(IFERROR(SEARCH("gathering",F46)>0,FALSE),IFERROR(SEARCH("gathering",I46)>0,FALSE)),"Gathering","Non-Gathering") -> Non-Gathering | AE46: Metallic | AF46: =VLOOKUP(A46,#REF!, 7, FALSE) -> #REF! | AG46: =VLOOKUP(A46,#REF!, 8, FALSE) -> #REF! | AI46: =VLOOKUP(A46,#REF!,40,FALSE) -> #REF!
A47: 400807497 | B47: DCP MIDSTREAM LP | C47: 4680 | D47: 42073 | E47: PIPELINE | F47: On May 10th, 2015, soil staining was noticed just south of the intersection of CR 71 & CR 16. DCP immediately blew down the line and began excavating the contaminated area to locate the suspected leaking 10" low pressure line below. A photo-ionization detector is being used onsite to determine the extent of contamination. Once contaminated area is suspected to be delineated, DCP will submit soil samples to the lab before backfilling area with clean fill dirt. More information will be included in the 10 day follow-up report. | G47: WELD | I47: Pipeline Corrosion | J47: 0 | K47: Corrosion | L47: Corrosion Type Unknown | M47: -104.3955 | N47: 40.0967 | O47: 0 | Q47: 1 | S47: 0 | U47: 0 | W47: 0 | Y47: NULL | AA47: NULL | AC47: =VLOOKUP(A47,'Basin Blanks Report'!$B$1:$F$222,3,FALSE) -> DENVER JULESBURG BASIN | AD47: =IF(OR(IFERROR(SEARCH("gathering",F47)>0,FALSE),IFERROR(SEARCH("gathering",I47)>0,FALSE)),"Gathering","Non-Gathering") -> Non-Gathering | AE47: Metallic | AF47: =VLOOKUP(A47,#REF!, 7, FALSE) -> #REF! | AG47: =VLOOKUP(A47,#REF!, 8, FALSE) -> #REF! | AI47: =VLOOKUP(A47,#REF!,40,FALSE) -> #REF!
A48: 400807606 | B48: NOBLE ENERGY INC | C48: 100322 | D48: 42073 | E48: FLOWLINE | F48: A hole developed in the flowline releasing crude oil and produced water. All production equipment was shut in and an excavation will be scheduled. Reichert 4 location. | G48: WELD | I48: flowline developed a leak | J48: The flowline will be repaired or replaced | K48: Unknown | L48: Unknown | M48: -104.67038 | N48: 40.32515 | O48: NULL | Q48: 0 | S48: NULL | U48: 0 | W48: 0 | Y48: NULL | AA48: NULL | AC48: =VLOOKUP(A48,'Basin Blanks Report'!$B$1:$F$222,3,FALSE) -> DENVER JULESBURG BASIN | AD48: =IF(OR(IFERROR(SEARCH("gathering",F48)>0,FALSE),IFERROR(SEARCH("gathering",I48)>0,FALSE)),"Gathering","Non-Gathering") -> Non-Gathering | AE48: Unknown | AF48: =VLOOKUP(A48,#REF!, 7, FALSE) -> #REF! | AG48: =VLOOKUP(A48,#REF!, 8, FALSE) -> #REF! | AI48: =VLOOKUP(A48,#REF!,40,FALSE) -> #REF!
A49: 400808000 | B49: NOBLE ENERGY INC | C49: 100322 | D49: 42073 | E49: FLOWLINE | F49: A hole developed at the flowline for the Lindsay C33-20 location. All production equipment was shut in and blown down. An excavation will be scheduled. | G49: WELD | I49: flowline leak detected | J49: the flowline will be replaced or repaired. | K49: Unknown | L49: Unknown | M49: -104.55987 | N49: 40.26891 | O49: 0 | Q49: NULL | S49: NULL | U49: 0 | W49: 0 | Y49: NULL | AA49: NULL | AC49: =VLOOKUP(A49,'Basin Blanks Report'!$B$1:$F$222,3,FALSE) -> DENVER JULESBURG BASIN | AD49: =IF(OR(IFERROR(SEARCH("gathering",F49)>0,FALSE),IFERROR(SEARCH("gathering",I49)>0,FALSE)),"Gathering","Non-Gathering") -> Non-Gathering | AE49: Unknown | AF49: =VLOOKUP(A49,#REF!, 7, FALSE) -> #REF! | AG49: =VLOOKUP(A49,#REF!, 8, FALSE) -> #REF! | AI49: =VLOOKUP(A49,#REF!,40,FALSE) -> #REF!
A50: 400808090 | B50: CAERUS PICEANCE LLC | C50: 10456 | D50: 42074 | E50: WELL | F50: After arriving on location, Caerus personnel discovered that a hammer union on the water line was leaking produced water. The well was immediately shut-in and the leaking component was repaired. | G50: YUMA | I50: After arriving on location, Caerus personnel discovered that a hammer union on the water line was leaking produced water. The well was immediately shut in and the leaking component was repaired. Equipment leak was caused by pressure buildup due to a workover at an adjacent location that shares a water tank with the Westerbert 23-8. During the workover the water line was shut off to the tank, but the Westerbert 23-8 was not shut in. | J50: Caerus will discuss with staff the importance of communication and making sure that all wells associated with a workover activity are shut in. | K50: Incorrect Operation | L50: Improper Procedures | M50: -102.32967 | N50: 39.9818 | O50: 0 | Q50: 0 | S50: 3 | U50: 0 | W50: 0 | Y50: NULL | AA50: NULL | AC50: =VLOOKUP(A50,'Basin Blanks Report'!$B$1:$F$222,3,FALSE) -> DENVER JULESBURG BASIN | AD50: =IF(OR(IFERROR(SEARCH("gathering",F50)>0,FALSE),IFERROR(SEARCH("gathering",I50)>0,FALSE)),"Gathering","Non-Gathering") -> Non-Gathering | AE50: Metallic | AF50: =VLOOKUP(A50,#REF!, 7, FALSE) -> #REF! | AG50: =VLOOKUP(A50,#REF!, 8, FALSE) -> #REF! | AI50: =VLOOKUP(A50,#REF!,40,FALSE) -> #REF!
A51: 400808146 | B51: NOBLE ENERGY INC | C51: 100322 | D51: 42074 | E51: FLOWLINE | F51: During maintenance activities a leak in the flowline was discovered. Impacted soil and groundwater over COGCC Table 910-1 standards was discovered. All production equipment has been shut in and blown down. An excavation will be scheduled. | G51: WELD | I51: Flowline developed a leak. | J51: The leaking flowline will be repaired or replaced. | K51: Unknown | L51: Unknown | M51: -104.6477 | N51: 40.35804 | O51: 0 | Q51: NULL | S51: NULL | U51: 0 | W51: 0 | Y51: NULL | AA51: NULL | AC51: =VLOOKUP(A51,'Basin Blanks Report'!$B$1:$F$222,3,FALSE) -> DENVER JULESBURG BASIN | AD51: =IF(OR(IFERROR(SEARCH("gathering",F51)>0,FALSE),IFERROR(SEARCH("gathering",I51)>0,FALSE)),"Gathering","Non-Gathering") -> Non-Gathering | AE51: Unknown | AF51: =VLOOKUP(A51,#REF!, 7, FALSE) -> #REF! | AG51: =VLOOKUP(A51,#REF!, 8, FALSE) -> #REF! | AI51: =VLOOKUP(A51,#REF!,40,FALSE) -> #REF!
A52: 400808425 | B52: KERR MCGEE OIL & GAS ONSHORE LP | C52: 47120 | D52: 42075 | E52: TANK BATTERY | F52: On March 5, 2015, oil and produced water was identified surfacing on the ground surface above a dumpline located north of the tank battery associated with the HSR-Rainin 13-29 well. The volume of the release in unknown. Internal corrosion was identified upon excavation of the dumpline. The impacted soil was excavated and confirmation soil samples were collected. Approximately 300 cubic yards of soil were excavated and transported to Buffalo Ridge Landfill in Keenesburg, Colorado for disposal. Confirmation soil samples were collected from the excavation and the analytical results and excavation details are provided below. A topographic Site Location Map showing the general location of the release is attached as Figure 1. | G52: WELD | I52: On March 5, 2015, oil and produced water was identified surfacing on the ground surface above a dumpline located north of the tank battery associated with the HSR-Rainin 13-29 well. The volume of the release in unknown. Internal corrosion was identified upon excavation of the dumpline. | J52: The corroded dumpline will be repaired. | K52: Corrosion | L52: Internal Corrosion | M52: -104.69223 | N52: 40.192707 | O52: NULL | Q52: 0 | S52: NULL | U52: 0 | W52: 0 | Y52: NULL | AA52: NULL | AC52: =VLOOKUP(A52,'Basin Blanks Report'!$B$1:$F$222,3,FALSE) -> DENVER JULESBURG BASIN | AD52: =IF(OR(IFERROR(SEARCH("gathering",F52)>0,FALSE),IFERROR(SEARCH("gathering",I52)>0,FALSE)),"Gathering","Non-Gathering") -> Non-Gathering | AE52: Metallic | AF52: =VLOOKUP(A52,#REF!, 7, FALSE) -> #REF! | AG52: =VLOOKUP(A52,#REF!, 8, FALSE) -> #REF! | AI52: =VLOOKUP(A52,#REF!,40,FALSE) -> #REF!
A53: 400808558 | B53: BONANZA CREEK ENERGY OPERATING COMPANY LLC | C53: 8960 | D53: 42075 | E53: FLOWLINE | F53: While conducting routine inspections, a release was observed along a flowline right of way. Approximately 7.4 bbl of oil and produced water were discharged to the ground surface. The well was shut-in immediately to stop the release. Incident response personnel were contacted to cleanup the discharged oil/water. The ground was frozen and the fluid was pooled on the ground surface. Following removal of the fluid, environmental personnel will collect soil samples from the area to ensure the remaining soil is compliant with COGCC Table 910-1 standards. | G53: JACKSON | I53: #N/A | J53: #N/A | K53: Unknown | L53: Unknown | M53: -106.24098 | N53: 40.781138 | O53: 7 | Q53: 0 | S53: 0 | U53: 0 | W53: 0 | Y53: NULL | AA53: NULL | AC53: NORTH PARK BASIN | AD53: =IF(OR(IFERROR(SEARCH("gathering",F53)>0,FALSE),IFERROR(SEARCH("gathering",I53)>0,FALSE)),"Gathering","Non-Gathering") -> Non-Gathering | AE53: Unknown | AF53: =VLOOKUP(A53,#REF!, 7, FALSE) -> #REF! | AG53: =VLOOKUP(A53,#REF!, 8, FALSE) -> #REF! | AI53: =VLOOKUP(A53,#REF!,40,FALSE) -> #REF!
A54: 400808815 | B54: PIONEER NATURAL RESOURCES USA INC | C54: 10084 | D54: 42075 | E54: WATER GATHERING SYSTEM/LINE | F54: Gathering line broke next to meter house causing a spill of approximately 5bbls to run across location and stop in sediment pond on the southeast edge of location. | G54: LAS ANIMAS | I54: Gathering line broke next to meter house causing a spill of approximately 5bbls to run across location and stop in sediment pond on the southeast edge of location. | J54: PVC arrived on location to begin repairs to the line this morning. Instead of just repairing the line, there will also be a design change. Piping from the 2 wells will converge to a valve and that piping will be rerouted around the meter house to avoid it. Work is expected to be finished tomorrow at the latest and the wells that are shut down to isolate this break will be restarted when work is complete. | K54: Unknown | L54: Unknown | M54: -104.89831 | N54: 37.18131 | O54: 0 | Q54: 0 | S54: 10 | U54: 0 | W54: 0 | Y54: NULL | AA54: NULL | AC54: RATON BASIN | AD54: =IF(OR(IFERROR(SEARCH("gathering",F54)>0,FALSE),IFERROR(SEARCH("gathering",I54)>0,FALSE)),"Gathering","Non-Gathering") -> Gathering | AE54: Unknown | AF54: =VLOOKUP(A54,#REF!, 7, FALSE) -> #REF! | AG54: =VLOOKUP(A54,#REF!, 8, FALSE) -> #REF! | AI54: =VLOOKUP(A54,#REF!,40,FALSE) -> #REF!
A55: 400808858 | B55: KERR MCGEE OIL & GAS ONSHORE LP | C55: 47120 | D55: 42075 | E55: TANK BATTERY | F55: On March 12, 2015, a dump line release was discovered during production line replacement activities at the Huber 4-27 production facility. Approximately 200 cubic yards of impacted material have been removed and transported to the Front Range Regional Landfill in Erie, Colorado for disposal. Excavation and sampling activities are on-going at this location and will be summarized in a supplemental report. | G55: WELD | I55: During routine maintenance, a release was discovered adjacent to the dump lines. | J55: The dump lines and associated equipment were replaced. | K55: Unknown | L55: Unknown | M55: -104.99461 | N55: 40.02917 | O55: 0 | Q55: NULL | S55: NULL | U55: 0 | W55: 0 | Y55: NULL | AA55: NULL | AC55: =VLOOKUP(A55,'Basin Blanks Report'!$B$1:$F$222,3,FALSE) -> DENVER JULESBURG BASIN | AD55: =IF(OR(IFERROR(SEARCH("gathering",F55)>0,FALSE),IFERROR(SEARCH("gathering",I55)>0,FALSE)),"Gathering","Non-Gathering") -> Non-Gathering | AE55: Unknown | AF55: =VLOOKUP(A55,#REF!, 7, FALSE) -> #REF! | AG55: =VLOOKUP(A55,#REF!, 8, FALSE) -> #REF! | AI55: =VLOOKUP(A55,#REF!,40,FALSE) -> #REF!
A56: 400812277 | B56: NOBLE ENERGY INC | C56: 100322 | D56: 42081 | E56: FLOWLINE | F56: The flowline for the Nix 28-8i4 developed a leak in a dry canal. The production equipment was shut in and an excavation will be performed. Soil lab confirmation sampling will be performed by a 3rd party environmental consultant to identify the extent of the excavation. The canal will be rebuilt with coordination from the ditch company. | G56: WELD | I56: Flowline developed a leak and surfaced. | J56: The line will be cut and capped below ground surface. Plugging and abandonment is being considered. | K56: Unknown | L56: Unknown | M56: -104.54757 | N56: 40.286102 | O56: NULL | Q56: 0 | S56: 0 | U56: 0 | W56: 0 | Y56: NULL | AA56: NULL | AC56: =VLOOKUP(A56,'Basin Blanks Report'!$B$1:$F$222,3,FALSE) -> DENVER JULESBURG BASIN | AD56: =IF(OR(IFERROR(SEARCH("gathering",F56)>0,FALSE),IFERROR(SEARCH("gathering",I56)>0,FALSE)),"Gathering","Non-Gathering") -> Non-Gathering | AE56: Unknown | AF56: =VLOOKUP(A56,#REF!, 7, FALSE) -> #REF! | AG56: =VLOOKUP(A56,#REF!, 8, FALSE) -> #REF! | AI56: =VLOOKUP(A56,#REF!,40,FALSE) -> #REF!
A57: 400812313 | B57: PIONEER NATURAL RESOURCES USA INC | C57: 10084 | D57: 42081 | E57: WATER GATHERING SYSTEM/LINE | F57: Buried 2" poly water gathering line failed on location and aproximately 2 bbls of produced water spread west across the pad and came to a stop a the entrance of the well pad. The well was shut off upon discovery. This water is normally surface discharged at CDPS permitted Franvilo Outfall 230. | G57: LAS ANIMAS | I57: Someone closed the valve at the Franvilo 230 outfall, causing pressure to build up in the system and the line broke near the Franvilo 22-35 wellhead. The well was shut off immediately upon discovery. | J57: Lease operators will be spoken to about gathering system and outfall operation procedures. A written statement will be kept on file from the repsonsible person(s). The line was repaired and the well and outfall are back to normal operations. | K57: Incorrect Operation | L57: Valve Misalignment | M57: -104.64479 | N57: 37.21743 | O57: 0 | Q57: 0 | S57: 2 | U57: 0 | W57: 0 | Y57: NULL | AA57: NULL | AC57: RATON BASIN | AD57: =IF(OR(IFERROR(SEARCH("gathering",F57)>0,FALSE),IFERROR(SEARCH("gathering",I57)>0,FALSE)),"Gathering","Non-Gathering") -> Gathering | AE57: Non-Metallic | AF57: =VLOOKUP(A57,#REF!, 7, FALSE) -> #REF! | AG57: =VLOOKUP(A57,#REF!, 8, FALSE) -> #REF! | AI57: =VLOOKUP(A57,#REF!,40,FALSE) -> #REF!
A58: 400812766 | B58: WHITING OIL & GAS CORPORATION | C58: 96155 | D58: 42082 | E58: TANK BATTERY | F58: A condensate leak was found on a flowline leading to a treater due to a loose union. The union was tightened stopping the leak. The liquid was contained with soil and the impacted soil will be excavated and placed on a liner for onsite remediation via soil shredding. | G58: WELD | I58: After excavating the impacted soil a union on the pipeline was discovered to have loosened as a result of corrosion, allowing liquid to be released through the threads. | J58: Whiting will be hydro-testing flow-lines on an annual basis to monitor line integrity. | K58: Corrosion | L58: Corrosion Type Unknown | M58: -103.9059 | N58: 40.836343 | O58: NULL | Q58: 0 | S58: NULL | U58: 0 | W58: 0 | Y58: NULL | AA58: NULL | AC58: =VLOOKUP(A58,'Basin Blanks Report'!$B$1:$F$222,3,FALSE) -> DENVER JULESBURG BASIN | AD58: =IF(OR(IFERROR(SEARCH("gathering",F58)>0,FALSE),IFERROR(SEARCH("gathering",I58)>0,FALSE)),"Gathering","Non-Gathering") -> Non-Gathering | AE58: Metallic | AF58: =VLOOKUP(A58,#REF!, 7, FALSE) -> #REF! | AG58: =VLOOKUP(A58,#REF!, 8, FALSE) -> #REF! | AI58: =VLOOKUP(A58,#REF!,40,FALSE) -> #REF!
A59: 400815996 | B59: CHEVRON USA INC | C59: 16700 | D59: 42089 | E59: FLOWLINE | F59: Today, Thursday (03-26-2015) at approximately 11:45 AM a leak occurred on the flow line at AC McLaughlin 16 (40.1377, -108.9215), due to internal corrosion on the elbow of the riser. Approximately 104 BBLs of produced water and 1 BBLs of oil were released. The master valves and the header valve were shut in immediately upon detection. Vacuum truck recovered an estimated 95 BBLs. Total spill was inside the pad berm except for 1.3 BBLs of produced water outside of berm. | G59: RIO BLANCO | I59: #N/A | J59: #N/A | K59: Corrosion | L59: Internal Corrosion | M59: -108.9215 | N59: 40.1377 | O59: 1 | Q59: 0 | S59: 104 | U59: 0 | W59: 0 | Y59: 0 | AA59: 0 | AC59: PICEANCE BASIN | AD59: =IF(OR(IFERROR(SEARCH("gathering",F59)>0,FALSE),IFERROR(SEARCH("gathering",I59)>0,FALSE)),"Gathering","Non-Gathering") -> Non-Gathering | AE59: Metallic | AF59: =VLOOKUP(A59,#REF!, 7, FALSE) -> #REF! | AG59: =VLOOKUP(A59,#REF!, 8, FALSE) -> #REF! | AI59: =VLOOKUP(A59,#REF!,40,FALSE) -> #REF!
A60: 400817777 | B60: BP AMERICA PRODUCTION COMPANY | C60: 10000 | D60: 42089 | E60: WATER GATHERING SYSTEM/LINE | F60: A Crossfire construction crew was on the SE corner of the Baird A1 location to remove a buried drip pot that was found to have an integrity issue. During the excavation of the drip pot the excavator bumped a 3-inch fiberglass produced water line that was buried adjacent to the drip pot. The produced water line cracked and released produced water. At the time of the incident the water line was already shut in. The fiberglass line broke and approximately 4-barrels of CBM produced water spilled into the excavated area. A vacuum truck was dispatched to the location and all of the standing produced water in the excavation was removed and sent to injection. The fiberglass line was repaired by 20:00 on 3/26/2015. | G60: LA PLATA | I60: A mechanical crew was on the location to remove an inline drip pot that is part of the gas gathering line. The crew was excavating the drip pot when the bucket of the excavator struck the 3" fiberglass produced water gathering line. The tooth on the bucket cracked the fiberglass line which was shut in at the time. The residual produced water spilled from the water line into the excavated area. The fiberglass line was subsequently replaced before it was put back into service. | J60: NULL | K60: Excavation Force Damage | L60: Line Strike | M60: -107.62074 | N60: 37.190789 | O60: 0 | Q60: 0 | S60: 4 | U60: 0 | W60: 0 | Y60: NULL | AA60: NULL | AC60: SAN JUAN BASIN | AD60: =IF(OR(IFERROR(SEARCH("gathering",F60)>0,FALSE),IFERROR(SEARCH("gathering",I60)>0,FALSE)),"Gathering","Non-Gathering") -> Gathering | AE60: Non-Metallic | AF60: =VLOOKUP(A60,#REF!, 7, FALSE) -> #REF! | AG60: =VLOOKUP(A60,#REF!, 8, FALSE) -> #REF! | AI60: =VLOOKUP(A60,#REF!,40,FALSE) -> #REF!
A61: 400816413 | B61: OXY USA WTP LP | C61: 66571 | D61: 42090 | E61: TANK BATTERY | F61: At approximately 8:00AM Friday (March 27, 2015) a contract water hauler discovered that Oxy had a leak outside of secondary containment. The pipeline was isolated to shut off the flow of water from the corroded 2" valve. The spill resulted from corrosion on the body of an above-ground 2" produced water valve. Knowles Trucking began recovering as much produced water from the ground as possible while all other produced water released was absorbed into the soil. No fluids migrated off the Logan Trail 28-10 Off-Loading Facility location boundary. | G61: GARFIELD | I61: #N/A | J61: #N/A | K61: Corrosion | L61: External Corrosion | M61: -108.26034 | N61: 39.399084 | O61: NULL | Q61: NULL | S61: NULL | U61: NULL | W61: NULL | Y61: NULL | AA61: NULL | AC61: PICEANCE BASIN | AD61: =IF(OR(IFERROR(SEARCH("gathering",F61)>0,FALSE),IFERROR(SEARCH("gathering",I61)>0,FALSE)),"Gathering","Non-Gathering") -> Non-Gathering | AE61: Metallic | AF61: =VLOOKUP(A61,#REF!, 7, FALSE) -> #REF! | AG61: =VLOOKUP(A61,#REF!, 8, FALSE) -> #REF! | AI61: =VLOOKUP(A61,#REF!,40,FALSE) -> #REF!
A62: 400816473 | B62: NOBLE ENERGY INC | C62: 100322 | D62: 42090 | E62: PIPELINE | F62: The flowline running from the injection well to the produced water tanks developed a leak. Impacts were discovered while plugging and abandonment of the injection well. | G62: WELD | I62: The produced water line developed a leak below ground surface | J62: The facility will be plugged and abandoned | K62: Unknown | L62: Unknown | M62: -104.94889 | N62: 40.05643 | O62: 0 | Q62: 0 | S62: NULL | U62: 0 | W62: 0 | Y62: NULL | AA62: NULL | AC62: =VLOOKUP(A62,'Basin Blanks Report'!$B$1:$F$222,3,FALSE) -> DENVER JULESBURG BASIN | AD62: =IF(OR(IFERROR(SEARCH("gathering",F62)>0,FALSE),IFERROR(SEARCH("gathering",I62)>0,FALSE)),"Gathering","Non-Gathering") -> Non-Gathering | AE62: Unknown | AF62: =VLOOKUP(A62,#REF!, 7, FALSE) -> #REF! | AG62: =VLOOKUP(A62,#REF!, 8, FALSE) -> #REF! | AI62: =VLOOKUP(A62,#REF!,40,FALSE) -> #REF!
A63: 400818062 | B63: OXY USA INC | C63: 66561 | D63: 42090 | E63: TANK BATTERY | F63: At approximately 8:00AM Friday (March 27, 2015) a contract water hauler discovered that Oxy had a leak outside of secondary containment. The pipeline was isolated to shut off the flow of water from the corroded 2" valve. The spill resulted from corrosion on the body of an above-ground 2" produced water valve. Knowles Trucking began recovering as much produced water from the ground as possible while all other produced water released was absorbed into the soil. No fluids migrated off the Logan Trail 28-10 Off-Loading Facility location boundary. | G63: GARFIELD | I63: The spill was the result of a corrosion related hole within the body of a 2" valve on the discharge pipeline. | J63: The corroded valve was replaced with a new valve. The system was pressure tested before being returned to service. | K63: Corrosion | L63: External Corrosion | M63: -108.26034 | N63: 39.399084 | O63: 0 | Q63: 0 | S63: 45 | U63: 0 | W63: 0 | Y63: NULL | AA63: NULL | AC63: PICEANCE BASIN | AD63: =IF(OR(IFERROR(SEARCH("gathering",F63)>0,FALSE),IFERROR(SEARCH("gathering",I63)>0,FALSE)),"Gathering","Non-Gathering") -> Non-Gathering | AE63: Metallic | AF63: =VLOOKUP(A63,#REF!, 7, FALSE) -> #REF! | AG63: =VLOOKUP(A63,#REF!, 8, FALSE) -> #REF! | AI63: =VLOOKUP(A63,#REF!,40,FALSE) -> #REF!
A64: 400818017 | B64: PIONEER NATURAL RESOURCES USA INC | C64: 10084 | D64: 42093 | E64: WATER GATHERING SYSTEM/LINE | F64: A break in the buried water line was discovered on the location near the Heartbeat 44-30 Tr wellhead. Approximately 10 bbls of produced water spilled out and ran NE across and off location. Water ran down into the stormwater drainage ditch along the south side of the road and continued to run east in that ditch where it then came to a stop before the gate. The well was shut off upon discovery. This water is usually surface discharged at nearby CDPS permitted Melbourne 217A outfall. | G64: LAS ANIMAS | I64: Lease Operator closed off the gathering valve to do a bucket test and did not realize the Tr well was shut-in and hooked to the original well. He did a bucket test on the original wel land left location. Pressure built behind the closed gathering valve and caused a pressure break in the Tr section of buried line. | J64: Lease Operators will be made aware of this flowline design and situation so they can prevent this from happening at other locations. The line has been repaired. | K64: Incorrect Operation | L64: Valve Misalignment | M64: -104.81452 | N64: 37.13609 | O64: 0 | Q64: 0 | S64: 10 | U64: 0 | W64: 0 | Y64: NULL | AA64: NULL | AC64: RATON BASIN | AD64: =IF(OR(IFERROR(SEARCH("gathering",F64)>0,FALSE),IFERROR(SEARCH("gathering",I64)>0,FALSE)),"Gathering","Non-Gathering") -> Gathering | AE64: Unknown | AF64: =VLOOKUP(A64,#REF!, 7, FALSE) -> #REF! | AG64: =VLOOKUP(A64,#REF!, 8, FALSE) -> #REF! | AI64: =VLOOKUP(A64,#REF!,40,FALSE) -> #REF!
A65: 400818078 | B65: OXY USA WTP LP | C65: 66571 | D65: 42093 | E65: PIPELINE | F65: At approximately 2:30pm, on March 30, 2015, an Oxy employee discovered evidence of a produced water spill originating on the edge of a pipeline ROW. The suspected produced water gathering pipeline was isolated to stop the spill of produced water. Excavation was started on March 31st, to determine the exact source of the release. Based on the spill footprint and known depth of the pipeline, it appears that the release will be greater than 100 barrels outside of secondary containment. An emergency berm was constructed on the edge of the ROW to capture any produced water before leaving the ROW. Oxy found no evidence of down-gradient surface water impacts in the drainage west of the spill based on an investigation conducted on March 31, 2015. | G65: GARFIELD | I65: The spill location was hydro-excavated to determine the point of pipeline failure. The spill was due to threading failure immediately behind the flange on the fiberglass pipeline. The failed portion of the pipeline was replaced and hydrotested to ensure additional spills would not occur. | J65: The failed portion of the pipeline was replaced and hydrotested to ensure additional spills would not occur. | K65: Pipe, Weld, or Joint Failure | L65: Poly Fitting or Fuse Failure | M65: -108.23262 | N65: 39.534316 | O65: 0 | Q65: 0 | S65: 106 | U65: 0 | W65: 0 | Y65: NULL | AA65: NULL | AC65: PICEANCE BASIN | AD65: =IF(OR(IFERROR(SEARCH("gathering",F65)>0,FALSE),IFERROR(SEARCH("gathering",I65)>0,FALSE)),"Gathering","Non-Gathering") -> Gathering | AE65: Metallic | AF65: =VLOOKUP(A65,#REF!, 7, FALSE) -> #REF! | AG65: =VLOOKUP(A65,#REF!, 8, FALSE) -> #REF! | AI65: =VLOOKUP(A65,#REF!,40,FALSE) -> #REF!
A66: 400819394 | B66: EXTRACTION OIL & GAS LLC | C66: 10459 | D66: 42093 | E66: TANK BATTERY | F66: This facility is operated by Noble Energy, but the ownership/liability of the well and for spill reporting and remediation is under Extraction Oil and Gas. On March 27, 2015, evidence of a release along a compromised section of the dump line was observed by Noble’s maintenance team. The quantity of condensate released into subsurface soils is unknown. Soil samples were collected on March 27, 2015, and laboratory analytical results, received on March 30, 2015, confirmed a historical release associated with the dump line. The line was replaced and approximately 10 yards of soil were removed. Additional information about the cleanup and associated analytical results will be submitted on a Supplemental Form 19 within 10 days of confirmation of the release. | G66: BOULDER | I66: #N/A | J66: #N/A | K66: Unknown | L66: Unknown | M66: -105.06548 | N66: 39.97463 | O66: 0 | Q66: NULL | S66: 0 | U66: 0 | W66: 0 | Y66: NULL | AA66: NULL | AC66: DENVER JULESBURG BASIN | AD66: =IF(OR(IFERROR(SEARCH("gathering",F66)>0,FALSE),IFERROR(SEARCH("gathering",I66)>0,FALSE)),"Gathering","Non-Gathering") -> Non-Gathering | AE66: Unknown | AF66: =VLOOKUP(A66,#REF!, 7, FALSE) -> #REF! | AG66: =VLOOKUP(A66,#REF!, 8, FALSE) -> #REF! | AI66: =VLOOKUP(A66,#REF!,40,FALSE) -> #REF!
A67: 400819636 | B67: BP AMERICA PRODUCTION COMPANY | C67: 10000 | D67: 42093 | E67: WATER GATHERING SYSTEM/LINE | F67: On March 30, 2015, a landowner, Ed Marquez, notified BP of a water leak on his property. BP immediately responded to the location on March 30, 2015, and found a Coal-bed Methane (CBM) produced water gathering line leaking produced water into the pipeline right-of-way. BP Operations staff isolated the water gathering line to stop the release. Additional BP and contract staff were dispatched to the location to contain the release. Initial assessment of the release area determined that the produced water had traveled from the pipeline ROW through a wooded area and entered a dry irrigation ditch, where water had not been turned on for the season. A vacuum truck was dispatched to the location on the same day to recover standing produced water that had collected in the irrigation ditch and low areas outside of the irrigation ditch. Approximately 160-barrels of CBM produced water were recovered from the area of the release. | G67: ARCHULETA | I67: Under investigation. | J67: NULL | K67: Unknown | L67: Unknown | M67: -107.42971 | N67: 37.03349 | O67: 0 | Q67: 0 | S67: NULL | U67: 0 | W67: 0 | Y67: NULL | AA67: NULL | AC67: SAN JUAN BASIN | AD67: =IF(OR(IFERROR(SEARCH("gathering",F67)>0,FALSE),IFERROR(SEARCH("gathering",I67)>0,FALSE)),"Gathering","Non-Gathering") -> Gathering | AE67: Unknown | AF67: =VLOOKUP(A67,#REF!, 7, FALSE) -> #REF! | AG67: =VLOOKUP(A67,#REF!, 8, FALSE) -> #REF! | AI67: =VLOOKUP(A67,#REF!,40,FALSE) -> #REF!
A68: 400818139 | B68: NOBLE ENERGY INC | C68: 100322 | D68: 42094 | E68: FLOWLINE | F68: A hole was detected in the flowline. The flowline was uncovered and impacts over COGCC standards were discovered in soil and groundwater. The site has been shut in and production has ceased. Remediation options are being evaluated for this unintentional release. | G68: WELD | I68: A segmant of the flowline running from the oil and gas well to the separator developed a leak. | J68: The section of flowline will be replaced or repaired. | K68: Unknown | L68: Unknown | M68: -104.56192 | N68: 40.319293 | O68: 0 | Q68: NULL | S68: 0 | U68: 0 | W68: 0 | Y68: NULL | AA68: NULL | AC68: =VLOOKUP(A68,'Basin Blanks Report'!$B$1:$F$222,3,FALSE) -> DENVER JULESBURG BASIN | AD68: =IF(OR(IFERROR(SEARCH("gathering",F68)>0,FALSE),IFERROR(SEARCH("gathering",I68)>0,FALSE)),"Gathering","Non-Gathering") -> Non-Gathering | AE68: Unknown | AF68: =VLOOKUP(A68,#REF!, 7, FALSE) -> #REF! | AG68: =VLOOKUP(A68,#REF!, 8, FALSE) -> #REF! | AI68: =VLOOKUP(A68,#REF!,40,FALSE) -> #REF!
A69: 400820924 | B69: OXY USA WTP LP | C69: 66571 | D69: 42099 | E69: WELL PAD | F69: At approximately 10:30am Sunday (April 5, 2015) an Oxy contract water hauler discovered that Oxy had a spill of produced water and condensate into the secondary containment. All spilled fluids were contained within the secondary containment and were recovered. Cause for the spill was the result of a failed ½” drain valve while the in-line 3” ball valve was left open. The ½” drain valve was replaced, the 3” ball valve was returned to the closed position, and the tank was returned to service. All fluids within the secondary containment were collected by a transport truck and returned to Oxy's produced water and condensate handling system. | G69: GARFIELD | I69: The cause for the spill was the result of a failed ½” drain valve. All fluids spilled into the lined secondary containment was removed and reintroduced into Oxy's produced water and condensate handling system. | J69: The ½” drain valve was replaced and the tank was returned to service. All fluid spilled into the lined secondary containment was removed and reintroduced into Oxy's produced water and condensate handling system. | K69: Equipment Failure | L69: Valve Failure | M69: -108.23262 | N69: 39.531811 | O69: 0 | Q69: 59 | S69: 81 | U69: 0 | W69: 0 | Y69: NULL | AA69: NULL | AC69: PICEANCE BASIN | AD69: =IF(OR(IFERROR(SEARCH("gathering",F69)>0,FALSE),IFERROR(SEARCH("gathering",I69)>0,FALSE)),"Gathering","Non-Gathering") -> Non-Gathering | AE69: Unknown | AF69: =VLOOKUP(A69,#REF!, 7, FALSE) -> #REF! | AG69: =VLOOKUP(A69,#REF!, 8, FALSE) -> #REF! | AI69: =VLOOKUP(A69,#REF!,40,FALSE) -> #REF!
A70: 400821099 | B70: NOBLE ENERGY INC | C70: 100322 | D70: 42099 | E70: FLOWLINE | F70: During operations a flowline leak was discovered. All production equipment was shut in and a repair was made. A site assessment and/or excavation will be scheduled. | G70: WELD | I70: The flowline developed a leak | J70: The flowline was repaired and will be pressure tested prior to being returned to production | K70: Unknown | L70: Unknown | M70: -104.58971 | N70: 40.18649 | O70: 0 | Q70: NULL | S70: NULL | U70: 0 | W70: 0 | Y70: NULL | AA70: NULL | AC70: =VLOOKUP(A70,'Basin Blanks Report'!$B$1:$F$222,3,FALSE) -> DENVER JULESBURG BASIN | AD70: =IF(OR(IFERROR(SEARCH("gathering",F70)>0,FALSE),IFERROR(SEARCH("gathering",I70)>0,FALSE)),"Gathering","Non-Gathering") -> Non-Gathering | AE70: Unknown | AF70: =VLOOKUP(A70,#REF!, 7, FALSE) -> #REF! | AG70: =VLOOKUP(A70,#REF!, 8, FALSE) -> #REF! | AI70: =VLOOKUP(A70,#REF!,40,FALSE) -> #REF!
A71: 400821348 | B71: PIONEER NATURAL RESOURCES USA INC | C71: 10084 | D71: 42100 | E71: WATER GATHERING SYSTEM/LINE | F71: We found a produced water spill near the Weston 24-23 A WD yesterday just east of location by the unnamed tributary to Wet Canyon. It’s the old buried line that was abandoned for a new upgraded line. The old line was capped on both ends but was not drained when it was abandoned. There was a small leak that let approximately 5 bbls of water spill out and run into the dry tributary of Wet Canyon. Water ran for about 400' before coming to s top in the tributary. Produced water did not reach Wet Canyon. The line was dug up today, bandaged up, and left abandoned. It should be 100% empty now since the leak occurred at a low point in that capped and abandoned section. | G71: LAS ANIMAS | I71: We found a produced water spill near the Weston 24-23 A WD yesterday just east of location by the unnamed tributary to Wet Canyon. It’s the old buried line that was abandoned for a new upgraded line. The old line was capped on both ends but was not drained when it was abandoned. There was a small leak that let approximately 5 bbls of water spill out and run into the dry tributary of Wet Canyon. Water ran for about 400' before coming to s top in the tributary. Produced water did not reach Wet Canyon. The line was dug up today, bandaged up, and left abandoned. It should be 100% empty now since the leak occurred at a low point in that capped and abandoned section. | J71: A proper SOP will be written for abandoning water lines. | K71: Incorrect Operation | L71: Line Not Properly Abandoned | M71: -104.85887 | N71: 37.15037 | O71: 0 | Q71: 0 | S71: 5 | U71: 0 | W71: 0 | Y71: NULL | AA71: NULL | AC71: RATON BASIN | AD71: =IF(OR(IFERROR(SEARCH("gathering",F71)>0,FALSE),IFERROR(SEARCH("gathering",I71)>0,FALSE)),"Gathering","Non-Gathering") -> Non-Gathering | AE71: Unknown | AF71: =VLOOKUP(A71,#REF!, 7, FALSE) -> #REF! | AG71: =VLOOKUP(A71,#REF!, 8, FALSE) -> #REF! | AI71: =VLOOKUP(A71,#REF!,40,FALSE) -> #REF!
A72: 400826699 | B72: KERR MCGEE GATHERING LLC | C72: 47121 | D72: 42100 | E72: PIPELINE | F72: On April 14, 2015, historical impacts were discovered during repairs and maintenance on the 38-0000-5140-3" Platte Valley Gathering Line. Approximately 300 cubic yards of impacted material have been excavated and transported to the Front Range Regional Landfill located in Erie, Colorado for disposal. Excavation activities are on-going at this location. | G72: WELD | H72: x | I72: A historical release was discovered during routine maintenance activities. | J72: The gathering line was flushed and repaired. | K72: Unknown | L72: Unknown | M72: -105.00116 | N72: 40.087304 | O72: 0 | Q72: NULL | S72: 0 | U72: 0 | W72: 0 | Y72: NULL | AA72: NULL | AC72: =VLOOKUP(A72,'Basin Blanks Report'!$B$1:$F$222,3,FALSE) -> DENVER JULESBURG BASIN | AD72: =IF(OR(IFERROR(SEARCH("gathering",F72)>0,FALSE),IFERROR(SEARCH("gathering",I72)>0,FALSE)),"Gathering","Non-Gathering") -> Gathering | AE72: Unknown | AF72: =VLOOKUP(A72,#REF!, 7, FALSE) -> #REF! | AG72: =VLOOKUP(A72,#REF!, 8, FALSE) -> #REF! | AI72: =VLOOKUP(A72,#REF!,40,FALSE) -> #REF!
A73: 400823479 | B73: KERR MCGEE OIL & GAS ONSHORE LP | C73: 47120 | D73: 42104 | E73: TANK BATTERY | F73: During a site inspection, oil and produced water were discovered on the ground surface near the separator resulting from a line failure at the HSR Van Schaack 4-11 site. Approximately 2 bbls of oil and produced water was released onto unlined containment. A hydro-vac truck was used to recover approximately 0.5 bbls of the released oil and produced water. The petroleum hydrocarbon impacted soil is being excavated. Groundwater was encountered in the excavation at approximately 7 feet bgs. Laboratory analytical results received on April 10, 2015 confirmed BTEX impacts to groundwater above the CGWQS. The groundwater analytical results are summarized in Table 1. Additional soil and groundwater samples will be collected from the excavation. The analytical results and excavation details will be provided in a supplemental report. A topographic Site Location Map showing the general location of the release is attached as Figure 1. | G73: ADAMS | I73: During a site inspection, oil and produced water were discovered on the ground surface near the separator resulting from a line failure at the HSR Van Schaack 4-11 site. Approximately 2 bbls of oil and produced water was released onto unlined containment. A hydro-vac truck was used to recover approximately 0.5 bbls of the released oil and produced water. The petroleum hydrocarbon impacted soil is being excavated. | J73: The dumpline will be repaired. | K73: Unknown | L73: Unknown | M73: -104.74999 | N73: 39.899697 | O73: 1 | Q73: 0 | S73: 1 | U73: 0 | W73: 0 | Y73: NULL | AA73: NULL | AC73: DENVER JULESBURG BASIN | AD73: =IF(OR(IFERROR(SEARCH("gathering",F73)>0,FALSE),IFERROR(SEARCH("gathering",I73)>0,FALSE)),"Gathering","Non-Gathering") -> Non-Gathering | AE73: Unknown | AF73: =VLOOKUP(A73,#REF!, 7, FALSE) -> #REF! | AG73: =VLOOKUP(A73,#REF!, 8, FALSE) -> #REF! | AI73: =VLOOKUP(A73,#REF!,40,FALSE) -> #REF!
A74: 400824016 | B74: CHEVRON USA INC | C74: 16700 | D74: 42105 | E74: FLOWLINE | F74: Saturday (04-11-2015) at approximately 2:10 PM a water injection leak occurred a 3” Steel injection line approx. 1350 feet west on injection well Fee 59. Approximately 29 BBLs of produced water and 0BBLs oil was released. The injection lateral line was immediately shut in upon detection. Vacuum truck recovered an estimated 15 BBLs of Produced Water. Affected Area will be water washed and soil samples will be taken. | G74: RIO BLANCO | I74: #N/A | J74: #N/A | K74: Unknown | L74: Unknown | M74: -108.84676 | N74: 40.122892 | O74: 0 | Q74: 0 | S74: 29 | U74: 0 | W74: 0 | Y74: 0 | AA74: 0 | AC74: PICEANCE BASIN | AD74: =IF(OR(IFERROR(SEARCH("gathering",F74)>0,FALSE),IFERROR(SEARCH("gathering",I74)>0,FALSE)),"Gathering","Non-Gathering") -> Non-Gathering | AE74: Metallic | AF74: =VLOOKUP(A74,#REF!, 7, FALSE) -> #REF! | AG74: =VLOOKUP(A74,#REF!, 8, FALSE) -> #REF! | AI74: =VLOOKUP(A74,#REF!,40,FALSE) -> #REF!
A75: 400824273 | B75: DCP MIDSTREAM LP | C75: 4680 | D75: 42107 | E75: PIPELINE | F75: DCP was called onsite to investigate a leaky valve. Remediation activities began immediately and the area around the valve was excavated to reveal what appeared to be more than a barrel of condensate released throughout the soil. DCP is currently using a hand held Photo-Ionization Detector to help guide the excavation. Once contamination is believed to be delineated, confirmation soil samples will be submitted to the lab. At this time, DCP believes there is a possibility that ground water could have been impacted. More information will be submitted in the 10 day follow up. | G75: WELD | I75: A leaky valve on a drip station loadout point was the cause of the soil to become impacted by hydrocarbons. | J75: The valve will be replaced as soon as excavation activities are completed. | K75: Equipment Failure | L75: Valve Failure | M75: -105.02862 | N75: 40.11008 | O75: 0 | Q75: 4 | S75: 0 | U75: 0 | W75: 0 | Y75: NULL | AA75: NULL | AC75: =VLOOKUP(A75,'Basin Blanks Report'!$B$1:$F$222,3,FALSE) -> DENVER JULESBURG BASIN | AD75: =IF(OR(IFERROR(SEARCH("gathering",F75)>0,FALSE),IFERROR(SEARCH("gathering",I75)>0,FALSE)),"Gathering","Non-Gathering") -> Non-Gathering | AE75: Unknown | AF75: =VLOOKUP(A75,#REF!, 7, FALSE) -> #REF! | AG75: =VLOOKUP(A75,#REF!, 8, FALSE) -> #REF! | AI75: =VLOOKUP(A75,#REF!,40,FALSE) -> #REF!
A76: 400825358 | B76: PDC ENERGY INC | C76: 69175 | D76: 42108 | E76: TANK BATTERY | F76: On April 14, 2015, a historic release was discovered during production line replacement at the Waste Services 21-35 production facility. Excavation activities are on-going and will be summarized in a subsequent Supplemental Form 19. Groundwater has not been encountered during initial excavation activities. | G76: WELD | H76: x | I76: A historic release was discovered during production line replacement activities. | J76: Production lines were replaced and routine pressure testing will be completed. | K76: Unknown | L76: Unknown | M76: -104.51974 | N76: 40.187742 | O76: 0 | Q76: NULL | S76: NULL | U76: 0 | W76: 0 | Y76: NULL | AA76: NULL | AC76: =VLOOKUP(A76,'Basin Blanks Report'!$B$1:$F$222,3,FALSE) -> DENVER JULESBURG BASIN | AD76: =IF(OR(IFERROR(SEARCH("gathering",F76)>0,FALSE),IFERROR(SEARCH("gathering",I76)>0,FALSE)),"Gathering","Non-Gathering") -> Non-Gathering | AE76: Unknown | AF76: =VLOOKUP(A76,#REF!, 7, FALSE) -> #REF! | AG76: =VLOOKUP(A76,#REF!, 8, FALSE) -> #REF! | AI76: =VLOOKUP(A76,#REF!,40,FALSE) -> #REF!
A77: 400826074 | B77: TEP ROCKY MOUNTAIN LLC | C77: 96850 | D77: 42108 | E77: TANK BATTERY | F77: The release was caused by corrosion of a buried condensate transfer pipeline and was discovered during routine pressure testing of the lines. The compromised line was excavated for repair and stained soil was encountered. The total volume will be determined when the excavation activities are completed. | G77: GARFIELD | I77: The release was caused by corrosion of the metal on a buried condensate dump line. It was discovered during routine pressure test to check the integrity of the line. The leaking line allowed produced water to migrate out into the subsurface soils. The cause of the historical release is unknown. | J77: Due to corrosion of metal piping throughout the field, all newly installed and repaired lines are being replaced with lines with an epoxy type coating on the inside of the pipe which greatly reduces potential corrosion of the metal and subsequent line failures. | K77: Corrosion | L77: Internal Corrosion | M77: -108.0818 | N77: 39.472147 | O77: 0 | Q77: NULL | S77: NULL | U77: 0 | W77: 0 | Y77: NULL | AA77: NULL | AC77: PICEANCE BASIN | AD77: =IF(OR(IFERROR(SEARCH("gathering",F77)>0,FALSE),IFERROR(SEARCH("gathering",I77)>0,FALSE)),"Gathering","Non-Gathering") -> Non-Gathering | AE77: Metallic | AF77: =VLOOKUP(A77,#REF!, 7, FALSE) -> #REF! | AG77: =VLOOKUP(A77,#REF!, 8, FALSE) -> #REF! | AI77: =VLOOKUP(A77,#REF!,40,FALSE) -> #REF!
A78: 400827243 | B78: NOBLE ENERGY INC | C78: 100322 | D78: 42111 | E78: TANK BATTERY | F78: During operations the flowline leading from the separator to the oil tank developed a leak. The facility was shut in and remediation will be scheduled. | G78: WELD | I78: The line running from the separator to the oil tank developed a leak | J78: The line will be replaced | K78: Unknown | L78: Unknown | M78: -104.88036 | N78: 40.26231 | O78: 0 | Q78: NULL | S78: 0 | U78: 0 | W78: 0 | Y78: NULL | AA78: NULL | AC78: =VLOOKUP(A78,'Basin Blanks Report'!$B$1:$F$222,3,FALSE) -> DENVER JULESBURG BASIN | AD78: =IF(OR(IFERROR(SEARCH("gathering",F78)>0,FALSE),IFERROR(SEARCH("gathering",I78)>0,FALSE)),"Gathering","Non-Gathering") -> Non-Gathering | AE78: Unknown | AF78: =VLOOKUP(A78,#REF!, 7, FALSE) -> #REF! | AG78: =VLOOKUP(A78,#REF!, 8, FALSE) -> #REF! | AI78: =VLOOKUP(A78,#REF!,40,FALSE) -> #REF!
A79: 400829125 | B79: DCP MIDSTREAM LP | C79: 4680 | D79: 42115 | E79: PIPELINE | F79: On 4/21/2015, Noble Energy contacted DCP Midstream about a line releasing just off of CR 40 1/2, near its intersection with CR 5. The line was immediately shut off and blown down. Locates were called in and a request to close a lane on CR 40 1/2 were submitted in order to perform our excavation and repair as soon as possible. A 3rd party soil remediation company will be onsite with a hand held photo-ionization detector (PID) to help determine the extent of the hydrocarbon impacted soils. More information will be provided in the 10-day follow up report. | G79: WELD | I79: Pipeline corrosion. A hole was formed in the bottom of the pipeline directly under CR 40.5. | J79: The pipeline was replaced and wrapped to prevent further release due to corrosion in the area. | K79: Corrosion | L79: Corrosion Type Unknown | M79: -105.02276 | N79: 40.284042 | O79: 0 | Q79: 2 | S79: 0 | U79: 0 | W79: 0 | Y79: NULL | AA79: NULL | AC79: =VLOOKUP(A79,'Basin Blanks Report'!$B$1:$F$222,3,FALSE) -> DENVER JULESBURG BASIN | AD79: =IF(OR(IFERROR(SEARCH("gathering",F79)>0,FALSE),IFERROR(SEARCH("gathering",I79)>0,FALSE)),"Gathering","Non-Gathering") -> Non-Gathering | AE79: Metallic | AF79: =VLOOKUP(A79,#REF!, 7, FALSE) -> #REF! | AG79: =VLOOKUP(A79,#REF!, 8, FALSE) -> #REF! | AI79: =VLOOKUP(A79,#REF!,40,FALSE) -> #REF!
A80: 400830122 | B80: NOBLE ENERGY INC | C80: 100322 | D80: 42116 | E80: TANK BATTERY | F80: During operations the flowline running from the separator to the oil tank developed a leak. All production has been shut in and remediaiton will be assessed. | G80: WELD | I80: During operations the flowline running from the separator to the oil tanks developed a leak. | J80: The section will be repaired and pressure tested prior to returning to production | K80: Unknown | L80: Unknown | M80: -104.7915 | N80: 40.2695 | O80: 0 | Q80: NULL | S80: 0 | U80: 0 | W80: 0 | Y80: NULL | AA80: NULL | AC80: =VLOOKUP(A80,'Basin Blanks Report'!$B$1:$F$222,3,FALSE) -> DENVER JULESBURG BASIN | AD80: =IF(OR(IFERROR(SEARCH("gathering",F80)>0,FALSE),IFERROR(SEARCH("gathering",I80)>0,FALSE)),"Gathering","Non-Gathering") -> Non-Gathering | AE80: Unknown | AF80: =VLOOKUP(A80,#REF!, 7, FALSE) -> #REF! | AG80: =VLOOKUP(A80,#REF!, 8, FALSE) -> #REF! | AI80: =VLOOKUP(A80,#REF!,40,FALSE) -> #REF!
A81: 400829815 | B81: KERR MCGEE OIL & GAS ONSHORE LP | C81: 47120 | D81: 42117 | E81: TANK BATTERY | F81: Soil with historical petroleum hydrocarbon impacts was encountered beneath the dumplines while deconstructing the James E. Callow Gas Unit-63N66W /5SWSW location. There was no indication that the dumplines were leaking. The volume of the release is unknown. Excavation activities are ongoing at the site. Based on the volume of petroleum hydrocarbon impacted soil excavated to date, the release was reported to COGCC on April 23, 2015. Soil and groundwater samples will be collected from the excavation. The analytical results and excavation details will be provided in a supplemental report. A topographic Site Location Map showing the general location of the release is attached as Figure 1. | G81: WELD | H81: x | I81: Soil with historical petroleum hydrocarbon impact was encountered beneath the dumplines while deconstructing the James E. Callow Gas Unit-63N66W /5SWSW location. There was no indication that the dumplines were leaking. The volume of the release is unknown. | J81: The Kerr-McGee facility is being deconstructed and will be decommissioned. | K81: Unknown | L81: Unknown | M81: -104.80702 | N81: 40.2472 | O81: 0 | Q81: NULL | S81: NULL | U81: 0 | W81: 0 | Y81: NULL | AA81: NULL | AC81: =VLOOKUP(A81,'Basin Blanks Report'!$B$1:$F$222,3,FALSE) -> DENVER JULESBURG BASIN | AD81: =IF(OR(IFERROR(SEARCH("gathering",F81)>0,FALSE),IFERROR(SEARCH("gathering",I81)>0,FALSE)),"Gathering","Non-Gathering") -> Non-Gathering | AE81: Unknown | AF81: =VLOOKUP(A81,#REF!, 7, FALSE) -> #REF! | AG81: =VLOOKUP(A81,#REF!, 8, FALSE) -> #REF! | AI81: =VLOOKUP(A81,#REF!,40,FALSE) -> #REF!
A82: 400829988 | B82: CHEVRON USA INC | C82: 16700 | D82: 42117 | E82: FLOWLINE | F82: Today, Thursday (04-23-2015) at approximately 10:45 a leak occurred on the lateral line to AC McLaughlin 35. Approximately 30.1 BBLs of produced water and 0 BBLs oil were released. The lateral lines were shut in immediately upon detection. Vacuum truck recovered an estimated 30 BBLs. Cause was found to be loose bolts on the flange. The affected area will be water washed tomorrow and soil samples will be taken. | G82: RIO BLANCO | I82: #N/A | J82: #N/A | K82: Incorrect Operation | L82: Improper Installation | M82: -108.902 | N82: 40.1473 | O82: 0 | Q82: 0 | S82: 30.1 | U82: 0 | W82: 0 | Y82: 0 | AA82: 0 | AC82: PICEANCE BASIN | AD82: =IF(OR(IFERROR(SEARCH("gathering",F82)>0,FALSE),IFERROR(SEARCH("gathering",I82)>0,FALSE)),"Gathering","Non-Gathering") -> Non-Gathering | AE82: Unknown | AF82: =VLOOKUP(A82,#REF!, 7, FALSE) -> #REF! | AG82: =VLOOKUP(A82,#REF!, 8, FALSE) -> #REF! | AI82: =VLOOKUP(A82,#REF!,40,FALSE) -> #REF!
A83: 400831556 | B83: FOUNDATION ENERGY MANAGEMENT LLC | C83: 10112 | D83: 42117 | E83: FLOWLINE | F83: Injection line to the water plant broke and spilled approximately 10 bbls of filtered water on the lease road. A vac truck was dispatched immediately to pick up the free-standing water. The water did not did not leave the roadway and impact any surface water areas. | G83: RIO BLANCO | I83: Injection line into the battery leaked | J83: Pumper is regularily checking injection lines to ensure they're in good working order and no issues are identified. | K83: Unknown | L83: Unknown | M83: -109.0314 | N83: 39.72349 | O83: 0 | Q83: 0 | S83: 10 | U83: 0 | W83: 0 | Y83: NULL | AA83: NULL | AC83: DOUGLAS CREEK ARCH | AD83: =IF(OR(IFERROR(SEARCH("gathering",F83)>0,FALSE),IFERROR(SEARCH("gathering",I83)>0,FALSE)),"Gathering","Non-Gathering") -> Non-Gathering | AE83: Unknown | AF83: =VLOOKUP(A83,#REF!, 7, FALSE) -> #REF! | AG83: =VLOOKUP(A83,#REF!, 8, FALSE) -> #REF! | AI83: =VLOOKUP(A83,#REF!,40,FALSE) -> #REF!
A84: 400833480 | B84: FOUNDATION ENERGY MANAGEMENT LLC | C84: 10112 | D84: 42122 | E84: FLOWLINE | F84: A small leak was discovered on the oil dump line to the tanks at the Jillson Battery (causing <1 bbl oil to spill). When digging up the area to remove stained soil and repair the leak, a historical spill was discovered from the old water dumpline in the same area. | G84: WELD | I84: Line leak from water line. Still investigating the root cause of the historical contamination. | J84: Flowline testing periodically as well as on-site visual inspections of the flowline areas. | K84: Unknown | L84: Unknown | M84: -104.99175 | N84: 40.116608 | O84: NULL | Q84: NULL | S84: NULL | U84: 0 | W84: 0 | Y84: NULL | AA84: NULL | AC84: =VLOOKUP(A84,'Basin Blanks Report'!$B$1:$F$222,3,FALSE) -> DENVER JULESBURG BASIN | AD84: =IF(OR(IFERROR(SEARCH("gathering",F84)>0,FALSE),IFERROR(SEARCH("gathering",I84)>0,FALSE)),"Gathering","Non-Gathering") -> Non-Gathering | AE84: Unknown | AF84: =VLOOKUP(A84,#REF!, 7, FALSE) -> #REF! | AG84: =VLOOKUP(A84,#REF!, 8, FALSE) -> #REF! | AI84: =VLOOKUP(A84,#REF!,40,FALSE) -> #REF!
A85: 400834258 | B85: CHEVRON USA INC | C85: 16700 | D85: 42122 | E85: FLOWLINE | F85: Wednesday (04-29-2015) at approximately 8:00 AM a leak occurred on the injection line to Nikkle A 3 due to internal corrosion on a coated spool. Approximately 28.1 BBLs of produced water and 0 BBLs oil were released. The lateral lines were shut in immediately upon detection. Vacuum truck recovered an estimated 4 BBLs. Soil samples will be taken. | G85: RIO BLANCO | I85: #N/A | J85: #N/A | K85: Corrosion | L85: Internal Corrosion | M85: -108.7891 | N85: 40.1086 | O85: 0 | Q85: 0 | S85: 28.1 | U85: 0 | W85: 0 | Y85: 0 | AA85: 0 | AC85: PICEANCE BASIN | AD85: =IF(OR(IFERROR(SEARCH("gathering",F85)>0,FALSE),IFERROR(SEARCH("gathering",I85)>0,FALSE)),"Gathering","Non-Gathering") -> Non-Gathering | AE85: Metallic | AF85: =VLOOKUP(A85,#REF!, 7, FALSE) -> #REF! | AG85: =VLOOKUP(A85,#REF!, 8, FALSE) -> #REF! | AI85: =VLOOKUP(A85,#REF!,40,FALSE) -> #REF!
A86: 400833949 | B86: K P KAUFFMAN COMPANY INC | C86: 46290 | D86: 42124 | E86: FLOWLINE | F86: On April 14, 2015, the Colorado Oil and Gas Conservation Commission (COGCC) notified K.P. Kauffman Company, Inc. (KPK) of a flowline leak following the property owner’s formal complaint. On April 15, 2015, KPK meet with the property owner to investigate the flowline leak from the ground surface and to discuss remediation efforts. Due to heavy precipitation expected that over the nex few days, KPK removed the contaminated top soil present and installed booms around the area in order to prevent the contamination to extend outside the leak area. Such work was performed in the presence of the surface owner, his consultant, and KPK's consultant. | G86: WELD | I86: #N/A | J86: #N/A | K86: Unknown | L86: Unknown | M86: -104.85139 | N86: 40.0823 | O86: 0 | Q86: NULL | S86: NULL | U86: 0 | W86: 0 | Y86: NULL | AA86: NULL | AC86: =VLOOKUP(A86,'Basin Blanks Report'!$B$1:$F$222,3,FALSE) -> DENVER JULESBURG BASIN | AD86: =IF(OR(IFERROR(SEARCH("gathering",F86)>0,FALSE),IFERROR(SEARCH("gathering",I86)>0,FALSE)),"Gathering","Non-Gathering") -> Non-Gathering | AE86: Unknown | AF86: =VLOOKUP(A86,#REF!, 7, FALSE) -> #REF! | AG86: =VLOOKUP(A86,#REF!, 8, FALSE) -> #REF! | AI86: =VLOOKUP(A86,#REF!,40,FALSE) -> #REF!
A87: 400834447 | B87: CHEVRON USA INC | C87: 16700 | D87: 42125 | E87: FLOWLINE | F87: Friday (05-01-2015) at approximately 6:20 AM a leak occurred on the injection line to AC McLaughlin 63, due to internal corrosion on a 3" coated spool. Approximately 97.4 BBLs of produced water and 0 BBLs oil were released. The lateral lines were shut in immediately upon detection. Vacuum truck recovered an estimated 95 BBLs. Total spill was contained on location. | G87: RIO BLANCO | I87: #N/A | J87: #N/A | K87: Corrosion | L87: Internal Corrosion | M87: -108.9091 | N87: 40.1391 | O87: 0 | Q87: 0 | S87: 97.4 | U87: 0 | W87: 0 | Y87: 0 | AA87: 0 | AC87: PICEANCE BASIN | AD87: =IF(OR(IFERROR(SEARCH("gathering",F87)>0,FALSE),IFERROR(SEARCH("gathering",I87)>0,FALSE)),"Gathering","Non-Gathering") -> Non-Gathering | AE87: Metallic | AF87: =VLOOKUP(A87,#REF!, 7, FALSE) -> #REF! | AG87: =VLOOKUP(A87,#REF!, 8, FALSE) -> #REF! | AI87: =VLOOKUP(A87,#REF!,40,FALSE) -> #REF!
A88: 400835400 | B88: PIONEER NATURAL RESOURCES USA INC | C88: 10084 | D88: 42125 | E88: WATER GATHERING SYSTEM/LINE | F88: BAMM was installing rig anchors and struck a buried produced water line. Approximately 10 bbls of produced water spilled out onto location. No water left location. The spill was isolated as soon as possible. | G88: LAS ANIMAS | I88: BAMM was installing rig anchors and hit an unmarked line that didn't have a locate. | J88: The line has been repaired | K88: Other Outside Force Damage | L88: Line Strike | M88: -104.78181 | N88: 37.23215 | O88: 0 | Q88: 0 | S88: 10 | U88: 0 | W88: 0 | Y88: NULL | AA88: NULL | AC88: RATON BASIN | AD88: =IF(OR(IFERROR(SEARCH("gathering",F88)>0,FALSE),IFERROR(SEARCH("gathering",I88)>0,FALSE)),"Gathering","Non-Gathering") -> Non-Gathering | AE88: Unknown | AF88: =VLOOKUP(A88,#REF!, 7, FALSE) -> #REF! | AG88: =VLOOKUP(A88,#REF!, 8, FALSE) -> #REF! | AI88: =VLOOKUP(A88,#REF!,40,FALSE) -> #REF!
A89: 400836230 | B89: CHEVRON MIDCONTINENT LP | C89: 16695 | D89: 42128 | E89: GAS GATHERING SYSTEM | F89: UNDERGROUND PIPELINES, 4'-5' BELOW SURFACE, LEAKED TO SURFACE WITHIN A GRASS PASTURE. LANDOWNER NOTICED AND CALLED CHEVRON PERSONNEL. THE FRUITLAND COALBED METHANE WATER MIGRATED SOUTH WITH A SLIGHT SLOPE. THE PUDDLING VARIED FROM 30' WIDE AT THE SOURCE AND NARROWED TO .5' AT THE END OF THE FLOW. EXTENT WAS DETERMINED BY PACING OFF, AREA SKETCHED AND DIVIDED INTO SEGMENTS. EACH SEGMENT WAS CALCULATED AS TO VOLUME. SOIL SAMPLES WERE TAKEN FROM THE FLOW AREA. A BACKGROUND SAMPLE WAS ALSO TAKEN. BOTH WILL BE ANALYZED PER COLORADO TABLE 910. MEASURES TO BE TAKEN FOR PREVENTION WILL BE DECIDED AFTER THE CAUSE IS IDENTIFIED. | G89: LA PLATA | I89: The leak was identified as originating at a 3” line where it connected to the main line. | J89: This leak has been repaired by welding the line. Once the repairs were made the line was pressure tested with fresh water to 200 lbs for one hour, no leaks were found. | K89: Unknown | L89: Unknown | M89: -107.83065 | N89: 37.239 | O89: 0 | Q89: 0 | S89: 84 | U89: 0 | W89: 0 | Y89: NULL | AA89: NULL | AC89: SAN JUAN BASIN | AD89: =IF(OR(IFERROR(SEARCH("gathering",F89)>0,FALSE),IFERROR(SEARCH("gathering",I89)>0,FALSE)),"Gathering","Non-Gathering") -> Non-Gathering | AE89: Unknown | AF89: =VLOOKUP(A89,#REF!, 7, FALSE) -> #REF! | AG89: =VLOOKUP(A89,#REF!, 8, FALSE) -> #REF! | AI89: =VLOOKUP(A89,#REF!,40,FALSE) -> #REF!
A90: 400836478 | B90: DCP MIDSTREAM LP | C90: 4680 | D90: 42128 | E90: PIPELINE | F90: On Monday May 4th, DCP was contacted about a potential pipeline leak near the subdivision of Eaton Commons in Eaton, CO. DCP personal responded to the call and identified a surface area with dyeing vegetation. DCP Personal blocked in the suspected line and made 811 One Calls on the location to identify other buried lines in the area. Soil removal and pipeline activities have not begun due to the weather, but will once conditions are more conducive to excavation. At that time the suspected leak area will be excavated, the pipeline repaired and all contaminated soil removed and disposed of at an approved waste disposal location. | G90: WELD | I90: #N/A | J90: #N/A | K90: Unknown | L90: Unknown | M90: -104.69697 | N90: 40.528161 | O90: NULL | Q90: NULL | S90: NULL | U90: 0 | W90: 0 | Y90: NULL | AA90: NULL | AC90: =VLOOKUP(A90,'Basin Blanks Report'!$B$1:$F$222,3,FALSE) -> DENVER JULESBURG BASIN | AD90: =IF(OR(IFERROR(SEARCH("gathering",F90)>0,FALSE),IFERROR(SEARCH("gathering",I90)>0,FALSE)),"Gathering","Non-Gathering") -> Non-Gathering | AE90: Unknown | AF90: =VLOOKUP(A90,#REF!, 7, FALSE) -> #REF! | AG90: =VLOOKUP(A90,#REF!, 8, FALSE) -> #REF! | AI90: =VLOOKUP(A90,#REF!,40,FALSE) -> #REF!
A91: 400836759 | B91: BURLINGTON RESOURCES OIL & GAS LP | C91: 26580 | D91: 42128 | E91: PIPELINE | F91: pipeline corroded allowing 29 bbls of produced water to come to surface and travel approximately 107' down the ROW near a road. Distances - 246' from surface water, no wetlands in area; uildings 683'; livestock 839'. water wells - unknown. depth of shallowest ground water unknown. Response - The pipeline was shuu-in and the area contained. Determined extent of contamination - Visual inspection as well as soil sampling; Further remediation - Will determine after sampling results are available; Describe measures taken to prevent reoccurance - Pipeline protection. | G91: LA PLATA | I91: see document # 400836759 | J91: Release was sampled on Monday 5/11/15 and the pipeline area excavatted with the pipeline repaired and backfilled. The surface was re-seeded and the pipeline is back on. I will have field results and map of the area to you as soon as possible. | K91: Corrosion | L91: Corrosion Type Unknown | M91: -107.85 | N91: 37.105892 | O91: 0 | Q91: 0 | S91: 29 | U91: 0 | W91: 0 | Y91: 0 | AA91: 0 | AC91: SAN JUAN BASIN | AD91: =IF(OR(IFERROR(SEARCH("gathering",F91)>0,FALSE),IFERROR(SEARCH("gathering",I91)>0,FALSE)),"Gathering","Non-Gathering") -> Non-Gathering | AE91: Metallic | AF91: =VLOOKUP(A91,#REF!, 7, FALSE) -> #REF! | AG91: =VLOOKUP(A91,#REF!, 8, FALSE) -> #REF! | AI91: =VLOOKUP(A91,#REF!,40,FALSE) -> #REF!
A92: 400836521 | B92: NOBLE ENERGY INC | C92: 100322 | D92: 42129 | E92: TANK BATTERY | F92: During operations a leak occurred at the produced water vault and produced water line. Facility has been shut in and remediation options are being evaluated. | G92: WELD | I92: The water vault and prodcued water line developed a leak | J92: Repairs will be made | K92: Unknown | L92: Unknown | M92: -104.47618 | N92: 40.51442 | O92: 0 | Q92: 0 | S92: NULL | U92: 0 | W92: 0 | Y92: NULL | AA92: NULL | AC92: =VLOOKUP(A92,'Basin Blanks Report'!$B$1:$F$222,3,FALSE) -> DENVER JULESBURG BASIN | AD92: =IF(OR(IFERROR(SEARCH("gathering",F92)>0,FALSE),IFERROR(SEARCH("gathering",I92)>0,FALSE)),"Gathering","Non-Gathering") -> Non-Gathering | AE92: Unknown | AF92: =VLOOKUP(A92,#REF!, 7, FALSE) -> #REF! | AG92: =VLOOKUP(A92,#REF!, 8, FALSE) -> #REF! | AI92: =VLOOKUP(A92,#REF!,40,FALSE) -> #REF!
A93: 400837778 | B93: DCP MIDSTREAM LP | C93: 4680 | D93: 42132 | E93: FLOWLINE | F93: An unexpected shutdown of a compressor station during a pipeline cleaning event caused a DCP owned valve to spray condensate in the air which then affected an estimated three to five acres of grass. This grass area that has been affected has since been mowed and will be raked and the soil then sprayed with Terradis SW Bioserfactant to eliminate any hydrocarbons that may have impacted the soil. After 5 to 7 days, confirmation soil samples will be collected and sent to the lab to prove delineation. More information will be provided in the 10-day follow up report. | G93: WELD | I93: An unexpected shutdown of a compressor station during a pipeline cleaning event caused a DCP owned valve to break and spray condensate in the air. | J93: DCP has repaired this valve and is taking measures to prevent the over pressuring of this line during any shutdown event. | K93: Equipment Failure | L93: Overpressure | M93: -104.49172 | N93: 40.19395 | O93: 0 | Q93: 1 | S93: 0 | U93: 0 | W93: 0 | Y93: NULL | AA93: NULL | AC93: =VLOOKUP(A93,'Basin Blanks Report'!$B$1:$F$222,3,FALSE) -> DENVER JULESBURG BASIN | AD93: =IF(OR(IFERROR(SEARCH("gathering",F93)>0,FALSE),IFERROR(SEARCH("gathering",I93)>0,FALSE)),"Gathering","Non-Gathering") -> Non-Gathering | AE93: Unknown | AF93: =VLOOKUP(A93,#REF!, 7, FALSE) -> #REF! | AG93: =VLOOKUP(A93,#REF!, 8, FALSE) -> #REF! | AI93: =VLOOKUP(A93,#REF!,40,FALSE) -> #REF!
A94: 400837814 | B94: KERR MCGEE OIL & GAS ONSHORE LP | C94: 47120 | D94: 42133 | E94: WELL | F94: At the WCLI USX S #33-15P wellhead, a kill switch on a pumping unit failed causing the line to over pressurize. Approximately 1 barrel of oil was released outside of containment onto the ground surface. A vacuum truck was utilized to recover approximately 1 barrel of the released oil. Confirmation soil samples will be collected from the release area or excavation, as applicable. The analytical results and excavation details will be provided in a supplemental report. A topographic Site Location Map showing the general location of the release is attached as Figure 1. | G94: WELD | I94: At the WCLI USX S #33-15P wellhead, a kill switch on a pumping unit failed causing the line to over pressurize. Approximately 1 barrel of oil was released outside of containment onto the ground surface. A vacuum truck was utilized to recover approximately 1 barrel of the released oil. | J94: The kill switch on the pumping unit will be replaced and the line will be repaired. | K94: Equipment Failure | L94: Overpressure | M94: -105.00522 | N94: 40.26382 | O94: 1 | Q94: 0 | S94: 0 | U94: 0 | W94: 0 | Y94: NULL | AA94: NULL | AC94: =VLOOKUP(A94,'Basin Blanks Report'!$B$1:$F$222,3,FALSE) -> DENVER JULESBURG BASIN | AD94: =IF(OR(IFERROR(SEARCH("gathering",F94)>0,FALSE),IFERROR(SEARCH("gathering",I94)>0,FALSE)),"Gathering","Non-Gathering") -> Non-Gathering | AE94: Unknown | AF94: =VLOOKUP(A94,#REF!, 7, FALSE) -> #REF! | AG94: =VLOOKUP(A94,#REF!, 8, FALSE) -> #REF! | AI94: =VLOOKUP(A94,#REF!,40,FALSE) -> #REF!
A95: 400838502 | B95: K P KAUFFMAN COMPANY INC | C95: 46290 | D95: 42136 | E95: WELL | F95: An open excavation area was created to repair a damaged flowline at K.P. Kauffman Company’s Charles C Bell Tank Battery. Heavy rain fall caused condensate from the excavated contaminated soil to wash into the excavated area already filled with stromwater. The condensate contamination is estimated to be less than one (1) barrel based on the extent of the sheen on top of the water. A vac truck was brought in on May 8, 2015 to remove the top portion of water that held the oil sheen. Absorbent pads were also placed in the water to collect any small remaining oil presence. Because of the shallow water table and collection of stormwater in the excavation area, ground water may have been impacted. The surface area affected by stormwater collection is estimated to be 70 feet by 40 feet. The excavation area is roughly 20 feet wide by 10 feet long and 4 feet deep. | G95: WELD | I95: An open excavation area was created to repair a damaged flowline at K.P. Kauffman Company’s Charles C Bell Tank Battery. Heavy rain fall caused condensate from the excavated contaminated soil to wash into the excavated area already filled with stromwater. The condensate contamination is estimated to be less than one (1) barrel based on the extent of the sheen on top of the water. | J95: The flowline has been repaired and portions of it have been replaced with poly line. A vac truck was brought in on May 8, 2015 to remove the top portion of water that held the oil sheen. Absorbent pads were also placed in the water to collect any small remaining oil presence. Because of the shallow water table and collection of stormwater in the excavation area, ground water may have been impacted. The surface area affected by stormwater collection is estimated to be 70 feet by 40 feet. The excavation area is roughly 20 feet wide by 10 feet long and 4 feet deep. | K95: Unknown | L95: Unknown | M95: -104.7869 | N95: 40.140188 | O95: 0 | Q95: NULL | S95: 0 | U95: 0 | W95: 0 | Y95: NULL | AA95: NULL | AC95: =VLOOKUP(A95,'Basin Blanks Report'!$B$1:$F$222,3,FALSE) -> DENVER JULESBURG BASIN | AD95: =IF(OR(IFERROR(SEARCH("gathering",F95)>0,FALSE),IFERROR(SEARCH("gathering",I95)>0,FALSE)),"Gathering","Non-Gathering") -> Non-Gathering | AE95: Unknown | AF95: =VLOOKUP(A95,#REF!, 7, FALSE) -> #REF! | AG95: =VLOOKUP(A95,#REF!, 8, FALSE) -> #REF! | AI95: =VLOOKUP(A95,#REF!,40,FALSE) -> #REF!
A96: 400838706 | B96: XTO ENERGY INC | C96: 100264 | D96: 42136 | E96: WELL PAD | F96: Inlet line to the seperator ruptured causing a produced water spill. The well was immediately shut down and taken out of service. Water was not contained or recovered. Investigation to the root cause will follow. | G96: LAS ANIMAS | I96: External corrosion occured on a buried 3 inch riser due to improper installation and potential damage to pipe coating. | J96: Riser was replaced with coated pipe, primed and taped with Roscoat. Ditch was padded and backfilled to prevent pipe damage. | K96: Corrosion | L96: External Corrosion | M96: -104.93773 | N96: 37.064125 | O96: 0 | Q96: 0 | S96: 14 | U96: 0 | W96: 0 | Y96: NULL | AA96: NULL | AC96: RATON BASIN | AD96: =IF(OR(IFERROR(SEARCH("gathering",F96)>0,FALSE),IFERROR(SEARCH("gathering",I96)>0,FALSE)),"Gathering","Non-Gathering") -> Non-Gathering | AE96: Metallic | AF96: =VLOOKUP(A96,#REF!, 7, FALSE) -> #REF! | AG96: =VLOOKUP(A96,#REF!, 8, FALSE) -> #REF! | AI96: =VLOOKUP(A96,#REF!,40,FALSE) -> #REF!
A97: 400839162 | B97: PIONEER NATURAL RESOURCES USA INC | C97: 10084 | D97: 42137 | E97: WATER GATHERING SYSTEM/LINE | F97: A break in the produced water gathering line was discovered today along the road just east of the Shinarump 11-11 location. wells have been sut-in and valves been turned to isolate most of the water feeding the line at the break point. This is still ongoing to completely stop the spill flow out of the line break. A hole has been dug at the spill point and water trucks are pulling water from the hole as needed. Some water ran east across the road and into a dry arroyo. | G97: LAS ANIMAS | I97: A break in the produced water gathering line just east of the Shinarump 11-11 location allowed approximately 182 bbls of produced water to spill out. Water ran south down the road, then east through a culvert, then south into a dry arroyo where it went through another culvert and eventually came to a stop. Wells feeding the line were shut-in and valves been turned to isolate the spill. A hole was dug at the spill point and water trucks pulled approximately 80 bbls of water from the hole. | J97: the line has been repaired | K97: Unknown | L97: Unknown | M97: -104.86389 | N97: 37.18951 | O97: 0 | Q97: 0 | S97: 182 | U97: 0 | W97: 0 | Y97: NULL | AA97: NULL | AC97: RATON BASIN | AD97: =IF(OR(IFERROR(SEARCH("gathering",F97)>0,FALSE),IFERROR(SEARCH("gathering",I97)>0,FALSE)),"Gathering","Non-Gathering") -> Gathering | AE97: Unknown | AF97: =VLOOKUP(A97,#REF!, 7, FALSE) -> #REF! | AG97: =VLOOKUP(A97,#REF!, 8, FALSE) -> #REF! | AI97: =VLOOKUP(A97,#REF!,40,FALSE) -> #REF!
A98: 400839515 | B98: FOUNDATION ENERGY MANAGEMENT LLC | C98: 10112 | D98: 42137 | E98: PIPELINE | F98: A water line leaked yesterday evening 200 yards East of RMR Ranch #14-36 (API#05-125-11946). Foundation Energy Management, LLC. called the COGCC and spoke to Rob Young (COGCC Inspector) on going forward with getting the line cleaned up. As per the spill requirements, Foundation contacted the landowner and Yuma LEPC of the spill. The determination of how much was spilled is unknown because of the present of rainwater on the location’s surface. The well has been shut in and the line isolated. A backhoe is scheduled to get on site to repair the line today (if it can make it down from Sterling) and we are getting a vac truck to suck up the standing water/rainwater. | G98: YUMA | I98: A water line sprung a leak. | J98: Repair leak and periodically check flowlines. | K98: Unknown | L98: Unknown | M98: -102.58366 | N98: 40.091364 | O98: 0 | Q98: 0 | S98: 13 | U98: 0 | W98: 0 | Y98: NULL | AA98: NULL | AC98: =VLOOKUP(A98,'Basin Blanks Report'!$B$1:$F$222,3,FALSE) -> DENVER JULESBURG BASIN | AD98: =IF(OR(IFERROR(SEARCH("gathering",F98)>0,FALSE),IFERROR(SEARCH("gathering",I98)>0,FALSE)),"Gathering","Non-Gathering") -> Non-Gathering | AE98: Unknown | AF98: =VLOOKUP(A98,#REF!, 7, FALSE) -> #REF! | AG98: =VLOOKUP(A98,#REF!, 8, FALSE) -> #REF! | AI98: =VLOOKUP(A98,#REF!,40,FALSE) -> #REF!
A99: 400839599 | B99: LARAMIE ENERGY LLC | C99: 10433 | D99: 42137 | E99: WELL PAD | F99: A Piceance Energy employee observed water on the Hawxhurst 24-09 pad next to the seperator at approximately 7:00 am on May 13, 2015. Piceance Energy immediately shut down the 24-09, 24-10B and 24-15A wells and began to excavate the soil around the dumpline. A 2" hole was found on the dumpline next to the seperator and was repaired. The leak likely began around 5:00 pm on May 12th and approx. 180 bbls spilled onto the well pad surface. All of the water spilled was contained on the pad. A vacuum truck was used and 130 bbls of water were recovered. A PID was used to determine the vertical extent and impacted soil was excavated around the dump line. Approximately 5 cubic yards of soil were excavated and placed on the pad. A composite sample from the excavated sample was collected for Table 910 analysis and screened with PetroFlag. The PetroFlag result was 43 ppm. Confirmation samples of the excavated soil will be completed pending lab analysis. | G99: MESA | I99: #N/A | J99: #N/A | K99: Unknown | L99: Unknown | M99: -107.93567 | N99: 39.25939 | O99: 0 | Q99: 0 | S99: 180 | U99: 0 | W99: 0 | Y99: 0 | AA99: 0 | AC99: PICEANCE BASIN | AD99: =IF(OR(IFERROR(SEARCH("gathering",F99)>0,FALSE),IFERROR(SEARCH("gathering",I99)>0,FALSE)),"Gathering","Non-Gathering") -> Non-Gathering | AE99: Unknown | AF99: =VLOOKUP(A99,#REF!, 7, FALSE) -> #REF! | AG99: =VLOOKUP(A99,#REF!, 8, FALSE) -> #REF! | AI99: =VLOOKUP(A99,#REF!,40,FALSE) -> #REF!
A100: 400840990 | B100: NOBLE ENERGY INC | C100: 100322 | D100: 42139 | E100: FLOWLINE | F100: During operation a flowline leak was detected near the wellhead at the Hoff 31-10 location. The well has been shut in and a site assessment to delineate groundwater and soil impacts is underway. Remediation options will be evaluated once the site assessment is completed. | G100: WELD | I100: The flowline developed a leak | J100: The flowline is being evaluated on a full replacement. | K100: Unknown | L100: Unknown | M100: -104.53421 | N100: 40.33234 | O100: 0 | Q100: NULL | S100: NULL | U100: 0 | W100: 0 | Y100: NULL | AA100: NULL | AC100: =VLOOKUP(A100,'Basin Blanks Report'!$B$1:$F$222,3,FALSE) -> DENVER JULESBURG BASIN | AD100: =IF(OR(IFERROR(SEARCH("gathering",F100)>0,FALSE),IFERROR(SEARCH("gathering",I100)>0,FALSE)),"Gathering","Non-Gathering") -> Non-Gathering | AE100: Unknown | AF100: =VLOOKUP(A100,#REF!, 7, FALSE) -> #REF! | AG100: =VLOOKUP(A100,#REF!, 8, FALSE) -> #REF! | AI100: =VLOOKUP(A100,#REF!,40,FALSE) -> #REF!
...

Sheet Basin Blanks Report
A1: wkt_geom | B1: trkg_num | C1: ID | D1: NAME | E1: Lat | F1: Long
A2: Point (225301.88694792380556464 4418937.33076254185289145) | B2: 401066122 | C2: 5 | D2: PICEANCE BASIN | E2: 39.87603 | F2: -108.21202
A3: Point (212207.42134096095105633 4432217.81210820376873016) | B3: 400805034 | C3: 5 | D3: PICEANCE BASIN | E3: 39.99114 | F3: -108.37075
A4: Point (218351.65339279582258314 4420428.69138516299426556) | B4: 400928623 | C4: 5 | D4: PICEANCE BASIN | E4: 39.887167 | F4: -108.29381
A5: Point (221723.65403464291011915 4409716.03824181109666824) | B5: 400903075 | C5: 5 | D5: PICEANCE BASIN | E5: 39.791914 | F5: -108.24988
A6: Point (218744.71096766035770997 4418467.91733968257904053) | B6: 400988434 | C6: 5 | D6: PICEANCE BASIN | E6: 39.86966 | F6: -108.28837
A7: Point (221705.04365554690593854 4409626.33708230871707201) | B7: 401059925 | C7: 5 | D7: PICEANCE BASIN | E7: 39.791101 | F7: -108.25006
A8: Point (220964.69570344634121284 4538232.53896433860063553) | B8: 400844350 | C8: 11 | D8: SAND WASH BASIN | E8: 40.947591 | F8: -108.31495
A9: Point (524333.73634620720986277 4487656.81166545115411282) | B9: 400763258 | C9: 12 | D9: DENVER JULESBURG BASIN | E9: 40.539301 | F9: -104.71265
A10: Point (563740.76309913408476859 4479714.43669730983674526) | B10: 400764687 | C10: 12 | D10: DENVER JULESBURG BASIN | E10: 40.46566 | F10: -104.24814
A11: Point (726486.21336037595756352 4479458.49585274793207645) | B11: 400765386 | C11: 12 | D11: DENVER JULESBURG BASIN | E11: 40.43495 | F11: -102.32982
A12: Point (536128.02382295462302864 4458890.22588541265577078) | B12: 400771524 | C12: 12 | D12: DENVER JULESBURG BASIN | E12: 40.279715 | F12: -104.57502
A13: Point (719842.50813464284874499 4477981.58284935262054205) | B13: 400774763 | C13: 12 | D13: DENVER JULESBURG BASIN | E13: 40.42344 | F13: -102.40858
... A222: Point (537452.78215012652799487 4480230.48348690010607243) | B222: 401158551 | C222: 12 | D222: DENVER JULESBURG BASIN | E222: 40.47191 | F222: -104.55818
